[{"lat":-60,"lng":-180,"u":4.599,"v":-1.131},{"lat":-60,"lng":-175,"u":2.637,"v":-2.283},{"lat":-60,"lng":-170,"u":3.345,"v":-2.802},{"lat":-60,"lng":-165,"u":5.335,"v":-1.405},{"lat":-60,"lng":-160,"u":4.711,"v":0.272},{"lat":-60,"lng":-155,"u":2.694,"v":0.215},{"lat":-60,"lng":-150,"u":3.235,"v":-0.843},{"lat":-60,"lng":-145,"u":5.274,"v":-0.584},{"lat":-60,"lng":-140,"u":4.818,"v":1.252},{"lat":-60,"lng":-135,"u":2.76,"v":2.442},{"lat":-60,"lng":-130,"u":3.13,"v":1.732},{"lat":-60,"lng":-125,"u":5.204,"v":0.778},{"lat":-60,"lng":-120,"u":4.92,"v":1.542},{"lat":-60,"lng":-115,"u":2.835,"v":3.213},{"lat":-60,"lng":-110,"u":3.032,"v":3.464},{"lat":-60,"lng":-105,"u":5.125,"v":2.075},{"lat":-60,"lng":-100,"u":5.015,"v":1.274},{"lat":-60,"lng":-95,"u":2.917,"v":2.254},{"lat":-60,"lng":-90,"u":2.94,"v":3.311},{"lat":-60,"lng":-85,"u":5.039,"v":2.512},{"lat":-60,"lng":-80,"u":5.103,"v":0.722},{"lat":-60,"lng":-75,"u":3.007,"v":0.265},{"lat":-60,"lng":-70,"u":2.855,"v":1.309},{"lat":-60,"lng":-65,"u":4.945,"v":1.617},{"lat":-60,"lng":-60,"u":5.184,"v":0.065},{"lat":-60,"lng":-55,"u":3.104,"v":-1.589},{"lat":-60,"lng":-50,"u":2.779,"v":-1.426},{"lat":-60,"lng":-45,"u":4.845,"v":-0.345},{"lat":-60,"lng":-40,"u":5.256,"v":-0.64},{"lat":-60,"lng":-35,"u":3.207,"v":-2.397},{"lat":-60,"lng":-30,"u":2.711,"v":-3.343},{"lat":-60,"lng":-25,"u":4.739,"v":-2.384},{"lat":-60,"lng":-20,"u":5.32,"v":-1.299},{"lat":-60,"lng":-15,"u":3.315,"v":-1.956},{"lat":-60,"lng":-10,"u":2.651,"v":-3.387},{"lat":-60,"lng":-5,"u":4.628,"v":-3.298},{"lat":-60,"lng":0,"u":5.375,"v":-1.656},{"lat":-60,"lng":5,"u":3.429,"v":-0.743},{"lat":-60,"lng":10,"u":2.601,"v":-1.603},{"lat":-60,"lng":15,"u":4.513,"v":-2.42},{"lat":-60,"lng":20,"u":5.42,"v":-1.372},{"lat":-60,"lng":25,"u":3.546,"v":0.509},{"lat":-60,"lng":30,"u":2.561,"v":0.93},{"lat":-60,"lng":35,"u":4.394,"v":-0.102},{"lat":-60,"lng":40,"u":5.455,"v":-0.31},{"lat":-60,"lng":45,"u":3.666,"v":1.276},{"lat":-60,"lng":50,"u":2.531,"v":2.783},{"lat":-60,"lng":55,"u":4.273,"v":2.404},{"lat":-60,"lng":60,"u":5.48,"v":1.203},{"lat":-60,"lng":65,"u":3.789,"v":1.439},{"lat":-60,"lng":70,"u":2.511,"v":3.025},{"lat":-60,"lng":75,"u":4.149,"v":3.657},{"lat":-60,"lng":80,"u":5.495,"v":2.406},{"lat":-60,"lng":85,"u":3.913,"v":1.167},{"lat":-60,"lng":90,"u":2.501,"v":1.704},{"lat":-60,"lng":95,"u":4.025,"v":2.895},{"lat":-60,"lng":100,"u":5.5,"v":2.498},{"lat":-60,"lng":105,"u":4.038,"v":0.66},{"lat":-60,"lng":110,"u":2.502,"v":-0.294},{"lat":-60,"lng":115,"u":3.9,"v":0.521},{"lat":-60,"lng":120,"u":5.494,"v":1.187},{"lat":-60,"lng":125,"u":4.162,"v":-0.001},{"lat":-60,"lng":130,"u":2.513,"v":-1.852},{"lat":-60,"lng":135,"u":3.776,"v":-2.12},{"lat":-60,"lng":140,"u":5.478,"v":-0.991},{"lat":-60,"lng":145,"u":4.286,"v":-0.775},{"lat":-60,"lng":150,"u":2.534,"v":-2.282},{"lat":-60,"lng":155,"u":3.653,"v":-3.54},{"lat":-60,"lng":160,"u":5.452,"v":-2.867},{"lat":-60,"lng":165,"u":4.407,"v":-1.487},{"lat":-60,"lng":170,"u":2.565,"v":-1.613},{"lat":-60,"lng":175,"u":3.533,"v":-2.991},{"lat":-60,"lng":180,"u":5.416,"v":-3.295},{"lat":-55,"lng":-180,"u":-4.078,"v":-1.924},{"lat":-55,"lng":-175,"u":-2.504,"v":-0.576},{"lat":-55,"lng":-170,"u":-3.859,"v":-1.036},{"lat":-55,"lng":-165,"u":-5.49,"v":-2.074},{"lat":-55,"lng":-160,"u":-4.202,"v":-1.491},{"lat":-55,"lng":-155,"u":-2.518,"v":0.43},{"lat":-55,"lng":-150,"u":-3.736,"v":1.345},{"lat":-55,"lng":-145,"u":-5.471,"v":0.493},{"lat":-55,"lng":-140,"u":-4.325,"v":-0.138},{"lat":-55,"lng":-135,"u":-2.543,"v":1.065},{"lat":-55,"lng":-130,"u":-3.614,"v":2.801},{"lat":-55,"lng":-125,"u":-5.441,"v":2.87},{"lat":-55,"lng":-120,"u":-4.446,"v":1.593},{"lat":-55,"lng":-115,"u":-2.577,"v":1.298},{"lat":-55,"lng":-110,"u":-3.495,"v":2.675},{"lat":-55,"lng":-105,"u":-5.402,"v":3.688},{"lat":-55,"lng":-100,"u":-4.563,"v":2.755},{"lat":-55,"lng":-95,"u":-2.622,"v":1.218},{"lat":-55,"lng":-90,"u":-3.379,"v":1.248},{"lat":-55,"lng":-85,"u":-5.352,"v":2.466},{"lat":-55,"lng":-80,"u":-4.677,"v":2.539},{"lat":-55,"lng":-75,"u":-2.676,"v":0.843},{"lat":-55,"lng":-70,"u":-3.268,"v":-0.552},{"lat":-55,"lng":-65,"u":-5.294,"v":-0.093},{"lat":-55,"lng":-60,"u":-4.786,"v":0.845},{"lat":-55,"lng":-55,"u":-2.739,"v":0.13},{"lat":-55,"lng":-50,"u":-3.162,"v":-1.779},{"lat":-55,"lng":-45,"u":-5.226,"v":-2.527},{"lat":-55,"lng":-40,"u":-4.889,"v":-1.524},{"lat":-55,"lng":-35,"u":-2.811,"v":-0.848},{"lat":-55,"lng":-30,"u":-3.061,"v":-1.984},{"lat":-55,"lng":-25,"u":-5.15,"v":-3.491},{"lat":-55,"lng":-20,"u":-4.986,"v":-3.244},{"lat":-55,"lng":-15,"u":-2.891,"v":-1.744},{"lat":-55,"lng":-10,"u":-2.967,"v":-1.335},{"lat":-55,"lng":-5,"u":-5.066,"v":-2.539},{"lat":-55,"lng":0,"u":-5.077,"v":-3.248},{"lat":-55,"lng":5,"u":-2.979,"v":-2.02},{"lat":-55,"lng":10,"u":-2.881,"v":-0.345},{"lat":-55,"lng":15,"u":-4.975,"v":-0.327},{"lat":-55,"lng":20,"u":-5.16,"v":-1.417},{"lat":-55,"lng":25,"u":-3.073,"v":-1.285},{"lat":-55,"lng":30,"u":-2.801,"v":0.52},{"lat":-55,"lng":35,"u":-4.877,"v":1.846},{"lat":-55,"lng":40,"u":-5.235,"v":1.279},{"lat":-55,"lng":45,"u":-3.175,"v":0.332},{"lat":-55,"lng":50,"u":-2.731,"v":1.062},{"lat":-55,"lng":55,"u":-4.773,"v":2.841},{"lat":-55,"lng":60,"u":-5.301,"v":3.318},{"lat":-55,"lng":65,"u":-3.281,"v":2.083},{"lat":-55,"lng":70,"u":-2.669,"v":1.293},{"lat":-55,"lng":75,"u":-4.663,"v":2.298},{"lat":-55,"lng":80,"u":-5.359,"v":3.528},{"lat":-55,"lng":85,"u":-3.393,"v":2.946},{"lat":-55,"lng":90,"u":-2.616,"v":1.233},{"lat":-55,"lng":95,"u":-4.549,"v":0.73},{"lat":-55,"lng":100,"u":-5.407,"v":1.795},{"lat":-55,"lng":105,"u":-3.509,"v":2.252},{"lat":-55,"lng":110,"u":-2.573,"v":0.81},{"lat":-55,"lng":115,"u":-4.431,"v":-0.906},{"lat":-55,"lng":120,"u":-5.445,"v":-0.873},{"lat":-55,"lng":125,"u":-3.629,"v":0.19},{"lat":-55,"lng":130,"u":-2.539,"v":-0.034},{"lat":-55,"lng":135,"u":-4.31,"v":-1.823},{"lat":-55,"lng":140,"u":-5.474,"v":-2.961},{"lat":-55,"lng":145,"u":-3.751,"v":-2.181},{"lat":-55,"lng":150,"u":-2.516,"v":-1.131},{"lat":-55,"lng":155,"u":-4.187,"v":-1.785},{"lat":-55,"lng":160,"u":-5.492,"v":-3.349},{"lat":-55,"lng":165,"u":-3.875,"v":-3.497},{"lat":-55,"lng":170,"u":-2.503,"v":-1.997},{"lat":-55,"lng":175,"u":-4.063,"v":-1.077},{"lat":-55,"lng":180,"u":-5.5,"v":-1.945},{"lat":-50,"lng":-180,"u":-7.38,"v":-3.052},{"lat":-50,"lng":-175,"u":-8.368,"v":-2.231},{"lat":-50,"lng":-170,"u":-6.536,"v":-0.386},{"lat":-50,"lng":-165,"u":-5.473,"v":0.147},{"lat":-50,"lng":-160,"u":-7.26,"v":-0.859},{"lat":-50,"lng":-155,"u":-8.398,"v":-1.188},{"lat":-50,"lng":-150,"u":-6.658,"v":0.339},{"lat":-50,"lng":-145,"u":-5.448,"v":2.001},{"lat":-50,"lng":-140,"u":-7.137,"v":1.848},{"lat":-50,"lng":-135,"u":-8.418,"v":0.722},{"lat":-50,"lng":-130,"u":-6.781,"v":0.93},{"lat":-50,"lng":-125,"u":-5.433,"v":2.618},{"lat":-50,"lng":-120,"u":-7.013,"v":3.533},{"lat":-50,"lng":-115,"u":-8.427,"v":2.527},{"lat":-50,"lng":-110,"u":-6.906,"v":1.345},{"lat":-50,"lng":-105,"u":-5.428,"v":1.891},{"lat":-50,"lng":-100,"u":-6.888,"v":3.254},{"lat":-50,"lng":-95,"u":-8.427,"v":3.132},{"lat":-50,"lng":-90,"u":-7.03,"v":1.434},{"lat":-50,"lng":-85,"u":-5.434,"v":0.429},{"lat":-50,"lng":-80,"u":-6.764,"v":1.215},{"lat":-50,"lng":-75,"u":-8.415,"v":2.018},{"lat":-50,"lng":-70,"u":-7.154,"v":0.978},{"lat":-50,"lng":-65,"u":-5.45,"v":-0.924},{"lat":-50,"lng":-60,"u":-6.641,"v":-1.383},{"lat":-50,"lng":-55,"u":-8.394,"v":-0.347},{"lat":-50,"lng":-50,"u":-7.277,"v":-0.078},{"lat":-50,"lng":-45,"u":-5.477,"v":-1.602},{"lat":-50,"lng":-40,"u":-6.519,"v":-3.085},{"lat":-50,"lng":-35,"u":-8.363,"v":-2.682},{"lat":-50,"lng":-30,"u":-7.397,"v":-1.406},{"lat":-50,"lng":-25,"u":-5.513,"v":-1.532},{"lat":-50,"lng":-20,"u":-6.401,"v":-3.036},{"lat":-50,"lng":-15,"u":-8.321,"v":-3.627},{"lat":-50,"lng":-10,"u":-7.514,"v":-2.324},{"lat":-50,"lng":-5,"u":-5.56,"v":-0.989},{"lat":-50,"lng":0,"u":-6.286,"v":-1.425},{"lat":-50,"lng":5,"u":-8.27,"v":-2.569},{"lat":-50,"lng":10,"u":-7.626,"v":-2.161},{"lat":-50,"lng":15,"u":-5.615,"v":-0.292},{"lat":-50,"lng":20,"u":-6.176,"v":0.723},{"lat":-50,"lng":25,"u":-8.21,"v":-0.056},{"lat":-50,"lng":30,"u":-7.734,"v":-0.748},{"lat":-50,"lng":35,"u":-5.68,"v":0.393},{"lat":-50,"lng":40,"u":-6.07,"v":2.229},{"lat":-50,"lng":45,"u":-8.141,"v":2.498},{"lat":-50,"lng":50,"u":-7.837,"v":1.326},{"lat":-50,"lng":55,"u":-5.754,"v":1.016},{"lat":-50,"lng":60,"u":-5.971,"v":2.435},{"lat":-50,"lng":65,"u":-8.063,"v":3.649},{"lat":-50,"lng":70,"u":-7.933,"v":2.934},{"lat":-50,"lng":75,"u":-5.835,"v":1.465},{"lat":-50,"lng":80,"u":-5.878,"v":1.479},{"lat":-50,"lng":85,"u":-7.978,"v":2.78},{"lat":-50,"lng":90,"u":-8.022,"v":3.055},{"lat":-50,"lng":95,"u":-5.924,"v":1.491},{"lat":-50,"lng":100,"u":-5.793,"v":0.059},{"lat":-50,"lng":105,"u":-7.885,"v":0.45},{"lat":-50,"lng":110,"u":-8.103,"v":1.447},{"lat":-50,"lng":115,"u":-6.02,"v":0.849},{"lat":-50,"lng":120,"u":-5.715,"v":-1.075},{"lat":-50,"lng":125,"u":-7.786,"v":-1.985},{"lat":-50,"lng":130,"u":-8.177,"v":-1.104},{"lat":-50,"lng":135,"u":-6.123,"v":-0.413},{"lat":-50,"lng":140,"u":-5.646,"v":-1.538},{"lat":-50,"lng":145,"u":-7.68,"v":-3.194},{"lat":-50,"lng":150,"u":-8.241,"v":-3.177},{"lat":-50,"lng":155,"u":-6.231,"v":-1.795},{"lat":-50,"lng":160,"u":-5.586,"v":-1.38},{"lat":-50,"lng":165,"u":-7.57,"v":-2.638},{"lat":-50,"lng":170,"u":-8.297,"v":-3.546},{"lat":-50,"lng":175,"u":-6.343,"v":-2.513},{"lat":-50,"lng":180,"u":-5.535,"v":-0.871},{"lat":-45,"lng":-180,"u":-7.075,"v":-0.946},{"lat":-45,"lng":-175,"u":-6.8,"v":-2.107},{"lat":-45,"lng":-170,"u":-8.875,"v":-2.173},{"lat":-45,"lng":-165,"u":-9.236,"v":-0.464},{"lat":-45,"lng":-160,"u":-7.176,"v":0.979},{"lat":-45,"lng":-155,"u":-6.73,"v":0.559},{"lat":-45,"lng":-150,"u":-8.771,"v":-0.401},{"lat":-45,"lng":-145,"u":-9.302,"v":0.257},{"lat":-45,"lng":-140,"u":-7.283,"v":2.132},{"lat":-45,"lng":-135,"u":-6.668,"v":2.873},{"lat":-45,"lng":-130,"u":-8.661,"v":1.835},{"lat":-45,"lng":-125,"u":-9.36,"v":1.067},{"lat":-45,"lng":-120,"u":-7.395,"v":2.103},{"lat":-45,"lng":-115,"u":-6.615,"v":3.553},{"lat":-45,"lng":-110,"u":-8.547,"v":3.268},{"lat":-45,"lng":-105,"u":-9.408,"v":1.693},{"lat":-45,"lng":-100,"u":-7.511,"v":1.172},{"lat":-45,"lng":-95,"u":-6.572,"v":2.291},{"lat":-45,"lng":-90,"u":-8.429,"v":2.968},{"lat":-45,"lng":-85,"u":-9.446,"v":1.716},{"lat":-45,"lng":-80,"u":-7.631,"v":-0.02},{"lat":-45,"lng":-75,"u":-6.539,"v":-0.107},{"lat":-45,"lng":-70,"u":-8.308,"v":0.964},{"lat":-45,"lng":-65,"u":-9.474,"v":0.863},{"lat":-45,"lng":-60,"u":-7.753,"v":-0.92},{"lat":-45,"lng":-55,"u":-6.516,"v":-2.257},{"lat":-45,"lng":-50,"u":-8.185,"v":-1.687},{"lat":-45,"lng":-45,"u":-9.492,"v":-0.679},{"lat":-45,"lng":-40,"u":-7.877,"v":-1.318},{"lat":-45,"lng":-35,"u":-6.503,"v":-3.035},{"lat":-45,"lng":-30,"u":-8.061,"v":-3.482},{"lat":-45,"lng":-25,"u":-9.5,"v":-2.188},{"lat":-45,"lng":-20,"u":-8.001,"v":-1.291},{"lat":-45,"lng":-15,"u":-6.5,"v":-2.192},{"lat":-45,"lng":-10,"u":-7.936,"v":-3.367},{"lat":-45,"lng":-5,"u":-9.497,"v":-2.754},{"lat":-45,"lng":0,"u":-8.126,"v":-0.975},{"lat":-45,"lng":5,"u":-6.508,"v":-0.381},{"lat":-45,"lng":10,"u":-7.812,"v":-1.388},{"lat":-45,"lng":15,"u":-9.484,"v":-1.845},{"lat":-45,"lng":20,"u":-8.25,"v":-0.411},{"lat":-45,"lng":25,"u":-6.526,"v":1.331},{"lat":-45,"lng":30,"u":-7.689,"v":1.328},{"lat":-45,"lng":35,"u":-9.461,"v":0.242},{"lat":-45,"lng":40,"u":-8.372,"v":0.396},{"lat":-45,"lng":45,"u":-6.555,"v":2.128},{"lat":-45,"lng":50,"u":-7.568,"v":3.244},{"lat":-45,"lng":55,"u":-9.427,"v":2.429},{"lat":-45,"lng":60,"u":-8.491,"v":1.291},{"lat":-45,"lng":65,"u":-6.593,"v":1.835},{"lat":-45,"lng":70,"u":-7.45,"v":3.327},{"lat":-45,"lng":75,"u":-9.384,"v":3.437},{"lat":-45,"lng":80,"u":-8.607,"v":1.877},{"lat":-45,"lng":85,"u":-6.641,"v":0.855},{"lat":-45,"lng":90,"u":-7.336,"v":1.634},{"lat":-45,"lng":95,"u":-9.331,"v":2.568},{"lat":-45,"lng":100,"u":-8.719,"v":1.687},{"lat":-45,"lng":105,"u":-6.699,"v":-0.211},{"lat":-45,"lng":110,"u":-7.227,"v":-0.788},{"lat":-45,"lng":115,"u":-9.269,"v":0.2},{"lat":-45,"lng":120,"u":-8.826,"v":0.542},{"lat":-45,"lng":125,"u":-6.765,"v":-0.953},{"lat":-45,"lng":130,"u":-7.123,"v":-2.578},{"lat":-45,"lng":135,"u":-9.198,"v":-2.372},{"lat":-45,"lng":140,"u":-8.927,"v":-1.169},{"lat":-45,"lng":145,"u":-6.84,"v":-1.276},{"lat":-45,"lng":150,"u":-7.025,"v":-2.861},{"lat":-45,"lng":155,"u":-9.119,"v":-3.675},{"lat":-45,"lng":160,"u":-9.022,"v":-2.564},{"lat":-45,"lng":165,"u":-6.924,"v":-1.262},{"lat":-45,"lng":170,"u":-6.933,"v":-1.688},{"lat":-45,"lng":175,"u":-9.032,"v":-2.947},{"lat":-45,"lng":180,"u":-9.11,"v":-2.74},{"lat":-40,"lng":-180,"u":-8.209,"v":-1.154},{"lat":-40,"lng":-175,"u":-7.736,"v":-0.066},{"lat":-40,"lng":-170,"u":-5.681,"v":-0.789},{"lat":-40,"lng":-165,"u":-6.069,"v":-1.589},{"lat":-40,"lng":-160,"u":-8.139,"v":-0.572},{"lat":-40,"lng":-155,"u":-7.838,"v":1.338},{"lat":-40,"lng":-150,"u":-5.755,"v":1.823},{"lat":-40,"lng":-145,"u":-5.97,"v":0.77},{"lat":-40,"lng":-140,"u":-8.062,"v":0.429},{"lat":-40,"lng":-135,"u":-7.934,"v":1.88},{"lat":-40,"lng":-130,"u":-5.837,"v":3.328},{"lat":-40,"lng":-125,"u":-5.877,"v":2.894},{"lat":-40,"lng":-120,"u":-7.976,"v":1.538},{"lat":-40,"lng":-115,"u":-8.023,"v":1.551},{"lat":-40,"lng":-110,"u":-5.926,"v":2.97},{"lat":-40,"lng":-105,"u":-5.792,"v":3.521},{"lat":-40,"lng":-100,"u":-7.883,"v":2.17},{"lat":-40,"lng":-95,"u":-8.104,"v":0.745},{"lat":-40,"lng":-90,"u":-6.022,"v":1.089},{"lat":-40,"lng":-85,"u":-5.714,"v":2.193},{"lat":-40,"lng":-80,"u":-7.784,"v":1.786},{"lat":-40,"lng":-75,"u":-8.178,"v":-0.101},{"lat":-40,"lng":-70,"u":-6.124,"v":-1.165},{"lat":-40,"lng":-65,"u":-5.645,"v":-0.409},{"lat":-40,"lng":-60,"u":-7.679,"v":0.321},{"lat":-40,"lng":-55,"u":-8.242,"v":-0.76},{"lat":-40,"lng":-50,"u":-6.232,"v":-2.568},{"lat":-40,"lng":-45,"u":-5.585,"v":-2.826},{"lat":-40,"lng":-40,"u":-7.568,"v":-1.603},{"lat":-40,"lng":-35,"u":-8.298,"v":-1.192},{"lat":-40,"lng":-30,"u":-6.345,"v":-2.517},{"lat":-40,"lng":-25,"u":-5.534,"v":-3.682},{"lat":-40,"lng":-20,"u":-7.453,"v":-2.924},{"lat":-40,"lng":-15,"u":-8.344,"v":-1.37},{"lat":-40,"lng":-10,"u":-6.462,"v":-1.274},{"lat":-40,"lng":-5,"u":-5.493,"v":-2.504},{"lat":-40,"lng":0,"u":-7.335,"v":-2.756},{"lat":-40,"lng":5,"u":-8.38,"v":-1.165},{"lat":-40,"lng":10,"u":-6.582,"v":0.332},{"lat":-40,"lng":15,"u":-5.462,"v":0},{"lat":-40,"lng":20,"u":-7.213,"v":-0.996},{"lat":-40,"lng":25,"u":-8.406,"v":-0.437},{"lat":-40,"lng":30,"u":-6.705,"v":1.47},{"lat":-40,"lng":35,"u":-5.441,"v":2.39},{"lat":-40,"lng":40,"u":-7.09,"v":1.491},{"lat":-40,"lng":45,"u":-8.423,"v":0.724},{"lat":-40,"lng":50,"u":-6.829,"v":1.759},{"lat":-40,"lng":55,"u":-5.43,"v":3.362},{"lat":-40,"lng":60,"u":-6.965,"v":3.312},{"lat":-40,"lng":65,"u":-8.428,"v":1.859},{"lat":-40,"lng":70,"u":-6.953,"v":1.332},{"lat":-40,"lng":75,"u":-5.429,"v":2.495},{"lat":-40,"lng":80,"u":-6.841,"v":3.359},{"lat":-40,"lng":85,"u":-8.424,"v":2.292},{"lat":-40,"lng":90,"u":-7.078,"v":0.578},{"lat":-40,"lng":95,"u":-5.439,"v":0.422},{"lat":-40,"lng":100,"u":-6.717,"v":1.521},{"lat":-40,"lng":105,"u":-8.408,"v":1.554},{"lat":-40,"lng":110,"u":-7.201,"v":-0.176},{"lat":-40,"lng":115,"u":-5.459,"v":-1.631},{"lat":-40,"lng":120,"u":-6.594,"v":-1.204},{"lat":-40,"lng":125,"u":-8.383,"v":-0.206},{"lat":-40,"lng":130,"u":-7.323,"v":-0.801},{"lat":-40,"lng":135,"u":-5.49,"v":-2.606},{"lat":-40,"lng":140,"u":-6.474,"v":-3.274},{"lat":-40,"lng":145,"u":-8.348,"v":-2.144},{"lat":-40,"lng":150,"u":-7.442,"v":-1.263},{"lat":-40,"lng":155,"u":-5.53,"v":-2.181},{"lat":-40,"lng":160,"u":-6.356,"v":-3.521},{"lat":-40,"lng":165,"u":-8.303,"v":-3.132},{"lat":-40,"lng":170,"u":-7.557,"v":-1.449},{"lat":-40,"lng":175,"u":-5.58,"v":-0.818},{"lat":-40,"lng":180,"u":-6.243,"v":-1.842},{"lat":-35,"lng":-180,"u":-2.527,"v":-2.633},{"lat":-35,"lng":-175,"u":-3.687,"v":-1.369},{"lat":-35,"lng":-170,"u":-5.46,"v":0.415},{"lat":-35,"lng":-165,"u":-4.374,"v":0.56},{"lat":-35,"lng":-160,"u":-2.555,"v":-0.504},{"lat":-35,"lng":-155,"u":-3.566,"v":-0.447},{"lat":-35,"lng":-150,"u":-5.427,"v":1.299},{"lat":-35,"lng":-145,"u":-4.493,"v":2.634},{"lat":-35,"lng":-140,"u":-2.594,"v":2.051},{"lat":-35,"lng":-135,"u":-3.448,"v":0.972},{"lat":-35,"lng":-130,"u":-5.383,"v":1.512},{"lat":-35,"lng":-125,"u":-4.609,"v":3.16},{"lat":-35,"lng":-120,"u":-2.642,"v":3.571},{"lat":-35,"lng":-115,"u":-3.334,"v":2.218},{"lat":-35,"lng":-110,"u":-5.33,"v":1.215},{"lat":-35,"lng":-105,"u":-4.721,"v":2.012},{"lat":-35,"lng":-100,"u":-2.7,"v":3.137},{"lat":-35,"lng":-95,"u":-3.225,"v":2.498},{"lat":-35,"lng":-90,"u":-5.268,"v":0.665},{"lat":-35,"lng":-85,"u":-4.828,"v":-0.011},{"lat":-35,"lng":-80,"u":-2.767,"v":0.949},{"lat":-35,"lng":-75,"u":-3.121,"v":1.417},{"lat":-35,"lng":-70,"u":-5.197,"v":0.006},{"lat":-35,"lng":-65,"u":-4.929,"v":-1.748},{"lat":-35,"lng":-60,"u":-2.842,"v":-1.763},{"lat":-35,"lng":-55,"u":-3.023,"v":-0.642},{"lat":-35,"lng":-50,"u":-5.118,"v":-0.715},{"lat":-35,"lng":-45,"u":-5.023,"v":-2.379},{"lat":-35,"lng":-40,"u":-2.925,"v":-3.464},{"lat":-35,"lng":-35,"u":-2.932,"v":-2.609},{"lat":-35,"lng":-30,"u":-5.031,"v":-1.378},{"lat":-35,"lng":-25,"u":-5.111,"v":-1.809},{"lat":-35,"lng":-20,"u":-3.016,"v":-3.229},{"lat":-35,"lng":-15,"u":-2.848,"v":-3.304},{"lat":-35,"lng":-10,"u":-4.937,"v":-1.688},{"lat":-35,"lng":-5,"u":-5.191,"v":-0.572},{"lat":-35,"lng":0,"u":-3.113,"v":-1.27},{"lat":-35,"lng":5,"u":-2.772,"v":-2.18},{"lat":-35,"lng":10,"u":-4.836,"v":-1.303},{"lat":-35,"lng":15,"u":-5.263,"v":0.619},{"lat":-35,"lng":20,"u":-3.217,"v":1.241},{"lat":-35,"lng":25,"u":-2.705,"v":0.259},{"lat":-35,"lng":30,"u":-4.73,"v":-0.136},{"lat":-35,"lng":35,"u":-5.325,"v":1.3},{"lat":-35,"lng":40,"u":-3.326,"v":2.902},{"lat":-35,"lng":45,"u":-2.646,"v":2.679},{"lat":-35,"lng":50,"u":-4.618,"v":1.408},{"lat":-35,"lng":55,"u":-5.379,"v":1.408},{"lat":-35,"lng":60,"u":-3.439,"v":2.907},{"lat":-35,"lng":65,"u":-2.597,"v":3.68},{"lat":-35,"lng":70,"u":-4.502,"v":2.519},{"lat":-35,"lng":75,"u":-5.423,"v":1.122},{"lat":-35,"lng":80,"u":-3.557,"v":1.443},{"lat":-35,"lng":85,"u":-2.558,"v":2.647},{"lat":-35,"lng":90,"u":-4.383,"v":2.424},{"lat":-35,"lng":95,"u":-5.458,"v":0.611},{"lat":-35,"lng":100,"u":-3.677,"v":-0.538},{"lat":-35,"lng":105,"u":-2.529,"v":0.144},{"lat":-35,"lng":110,"u":-4.261,"v":0.935},{"lat":-35,"lng":115,"u":-5.482,"v":-0.068},{"lat":-35,"lng":120,"u":-3.8,"v":-1.956},{"lat":-35,"lng":125,"u":-2.51,"v":-2.406},{"lat":-35,"lng":130,"u":-4.138,"v":-1.295},{"lat":-35,"lng":135,"u":-5.496,"v":-0.868},{"lat":-35,"lng":140,"u":-3.924,"v":-2.222},{"lat":-35,"lng":145,"u":-2.501,"v":-3.575},{"lat":-35,"lng":150,"u":-4.013,"v":-3.042},{"lat":-35,"lng":155,"u":-5.5,"v":-1.572},{"lat":-35,"lng":160,"u":-4.049,"v":-1.46},{"lat":-35,"lng":165,"u":-2.502,"v":-2.767},{"lat":-35,"lng":170,"u":-3.889,"v":-3.222},{"lat":-35,"lng":175,"u":-5.493,"v":-1.781},{"lat":-35,"lng":180,"u":-4.174,"v":-0.266},{"lat":-30,"lng":-180,"u":-1.479,"v":-0.705},{"lat":-30,"lng":-175,"u":0.222,"v":-1.779},{"lat":-30,"lng":-170,"u":1.488,"v":-1.384},{"lat":-30,"lng":-165,"u":-0.16,"v":0.508},{"lat":-30,"lng":-160,"u":-1.494,"v":1.606},{"lat":-30,"lng":-155,"u":0.097,"v":0.861},{"lat":-30,"lng":-150,"u":1.499,"v":0.08},{"lat":-30,"lng":-145,"u":-0.035,"v":1.089},{"lat":-30,"lng":-140,"u":-1.5,"v":2.858},{"lat":-30,"lng":-135,"u":-0.027,"v":3.096},{"lat":-30,"lng":-130,"u":1.499,"v":1.814},{"lat":-30,"lng":-125,"u":0.09,"v":1.297},{"lat":-30,"lng":-120,"u":-1.495,"v":2.524},{"lat":-30,"lng":-115,"u":-0.152,"v":3.638},{"lat":-30,"lng":-110,"u":1.489,"v":2.84},{"lat":-30,"lng":-105,"u":0.214,"v":1.204},{"lat":-30,"lng":-100,"u":-1.48,"v":1.003},{"lat":-30,"lng":-95,"u":-0.275,"v":2.169},{"lat":-30,"lng":-90,"u":1.468,"v":2.408},{"lat":-30,"lng":-85,"u":0.336,"v":0.8},{"lat":-30,"lng":-80,"u":-1.455,"v":-0.748},{"lat":-30,"lng":-75,"u":-0.397,"v":-0.463},{"lat":-30,"lng":-70,"u":1.438,"v":0.545},{"lat":-30,"lng":-65,"u":0.457,"v":0.037},{"lat":-30,"lng":-60,"u":-1.419,"v":-1.838},{"lat":-30,"lng":-55,"u":-0.516,"v":-2.756},{"lat":-30,"lng":-50,"u":1.398,"v":-1.83},{"lat":-30,"lng":-45,"u":0.574,"v":-0.979},{"lat":-30,"lng":-40,"u":-1.374,"v":-1.914},{"lat":-30,"lng":-35,"u":-0.631,"v":-3.458},{"lat":-30,"lng":-30,"u":1.347,"v":-3.371},{"lat":-30,"lng":-25,"u":0.687,"v":-1.848},{"lat":-30,"lng":-20,"u":-1.319,"v":-1.209},{"lat":-30,"lng":-15,"u":-0.742,"v":-2.28},{"lat":-30,"lng":-10,"u":1.288,"v":-3.106},{"lat":-30,"lng":-5,"u":0.795,"v":-2.013},{"lat":-30,"lng":0,"u":-1.255,"v":-0.237},{"lat":-30,"lng":5,"u":-0.848,"v":-0.005},{"lat":-30,"lng":10,"u":1.22,"v":-1.074},{"lat":-30,"lng":15,"u":0.898,"v":-1.13},{"lat":-30,"lng":20,"u":-1.182,"v":0.579},{"lat":-30,"lng":25,"u":-0.947,"v":2.049},{"lat":-30,"lng":30,"u":1.143,"v":1.628},{"lat":-30,"lng":35,"u":0.995,"v":0.578},{"lat":-30,"lng":40,"u":-1.102,"v":1.087},{"lat":-30,"lng":45,"u":-1.041,"v":2.831},{"lat":-30,"lng":50,"u":1.058,"v":3.469},{"lat":-30,"lng":55,"u":1.085,"v":2.287},{"lat":-30,"lng":60,"u":-1.013,"v":1.303},{"lat":-30,"lng":65,"u":-1.127,"v":2.113},{"lat":-30,"lng":70,"u":0.966,"v":3.393},{"lat":-30,"lng":75,"u":1.167,"v":2.971},{"lat":-30,"lng":80,"u":-0.918,"v":1.224},{"lat":-30,"lng":85,"u":-1.205,"v":0.498},{"lat":-30,"lng":90,"u":0.868,"v":1.455},{"lat":-30,"lng":95,"u":1.241,"v":2.054},{"lat":-30,"lng":100,"u":-0.816,"v":0.754},{"lat":-30,"lng":105,"u":-1.275,"v":-1.058},{"lat":-30,"lng":110,"u":0.763,"v":-1.218},{"lat":-30,"lng":115,"u":1.307,"v":-0.14},{"lat":-30,"lng":120,"u":-0.709,"v":-0.153},{"lat":-30,"lng":125,"u":-1.337,"v":-1.842},{"lat":-30,"lng":130,"u":0.653,"v":-3.115},{"lat":-30,"lng":135,"u":1.364,"v":-2.456},{"lat":-30,"lng":140,"u":-0.596,"v":-1.277},{"lat":-30,"lng":145,"u":-1.388,"v":-1.702},{"lat":-30,"lng":150,"u":0.539,"v":-3.239},{"lat":-30,"lng":155,"u":1.411,"v":-3.546},{"lat":-30,"lng":160,"u":-0.48,"v":-2.085},{"lat":-30,"lng":165,"u":-1.431,"v":-0.965},{"lat":-30,"lng":170,"u":0.42,"v":-1.654},{"lat":-30,"lng":175,"u":1.448,"v":-2.693},{"lat":-30,"lng":180,"u":-0.36,"v":-1.987},{"lat":-25,"lng":-180,"u":-0.257,"v":-0.311},{"lat":-25,"lng":-175,"u":-2.281,"v":0.434},{"lat":-25,"lng":-170,"u":-2.879,"v":-0.489},{"lat":-25,"lng":-165,"u":-0.88,"v":-0.982},{"lat":-25,"lng":-160,"u":-0.199,"v":0.393},{"lat":-25,"lng":-155,"u":-2.169,"v":2.145},{"lat":-25,"lng":-150,"u":-2.933,"v":2.165},{"lat":-25,"lng":-145,"u":-0.994,"v":0.999},{"lat":-25,"lng":-140,"u":-0.15,"v":0.98},{"lat":-25,"lng":-135,"u":-2.054,"v":2.567},{"lat":-25,"lng":-130,"u":-2.977,"v":3.614},{"lat":-25,"lng":-125,"u":-1.112,"v":2.715},{"lat":-25,"lng":-120,"u":-0.11,"v":1.389},{"lat":-25,"lng":-115,"u":-1.934,"v":1.708},{"lat":-25,"lng":-110,"u":-3.011,"v":3.057},{"lat":-25,"lng":-105,"u":-1.232,"v":3.101},{"lat":-25,"lng":-100,"u":-0.081,"v":1.438},{"lat":-25,"lng":-95,"u":-1.812,"v":0.236},{"lat":-25,"lng":-90,"u":-3.035,"v":0.862},{"lat":-25,"lng":-85,"u":-1.355,"v":1.76},{"lat":-25,"lng":-80,"u":-0.062,"v":0.9},{"lat":-25,"lng":-75,"u":-1.689,"v":-1.032},{"lat":-25,"lng":-70,"u":-3.049,"v":-1.686},{"lat":-25,"lng":-65,"u":-1.479,"v":-0.697},{"lat":-25,"lng":-60,"u":-0.054,"v":-0.238},{"lat":-25,"lng":-55,"u":-1.564,"v":-1.603},{"lat":-25,"lng":-50,"u":-3.053,"v":-3.172},{"lat":-25,"lng":-45,"u":-1.604,"v":-2.923},{"lat":-25,"lng":-40,"u":-0.055,"v":-1.579},{"lat":-25,"lng":-35,"u":-1.44,"v":-1.467},{"lat":-25,"lng":-30,"u":-3.046,"v":-2.878},{"lat":-25,"lng":-25,"u":-1.728,"v":-3.608},{"lat":-25,"lng":-20,"u":-0.067,"v":-2.4},{"lat":-25,"lng":-15,"u":-1.316,"v":-0.914},{"lat":-25,"lng":-10,"u":-3.029,"v":-1.136},{"lat":-25,"lng":-5,"u":-1.852,"v":-2.291},{"lat":-25,"lng":0,"u":-0.089,"v":-2.063},{"lat":-25,"lng":5,"u":-1.193,"v":-0.231},{"lat":-25,"lng":10,"u":-3.001,"v":0.971},{"lat":-25,"lng":15,"u":-1.973,"v":0.322},{"lat":-25,"lng":20,"u":-0.122,"v":-0.496},{"lat":-25,"lng":25,"u":-1.074,"v":0.451},{"lat":-25,"lng":30,"u":-2.964,"v":2.312},{"lat":-25,"lng":35,"u":-2.091,"v":2.758},{"lat":-25,"lng":40,"u":-0.164,"v":1.603},{"lat":-25,"lng":45,"u":-0.957,"v":1.081},{"lat":-25,"lng":50,"u":-2.917,"v":2.341},{"lat":-25,"lng":55,"u":-2.205,"v":3.643},{"lat":-25,"lng":60,"u":-0.216,"v":3.07},{"lat":-25,"lng":65,"u":-0.845,"v":1.516},{"lat":-25,"lng":70,"u":-2.86,"v":1.293},{"lat":-25,"lng":75,"u":-2.315,"v":2.521},{"lat":-25,"lng":80,"u":-0.277,"v":2.947},{"lat":-25,"lng":85,"u":-0.737,"v":1.478},{"lat":-25,"lng":90,"u":-2.795,"v":-0.104},{"lat":-25,"lng":95,"u":-2.42,"v":0.095},{"lat":-25,"lng":100,"u":-0.347,"v":1.136},{"lat":-25,"lng":105,"u":-0.636,"v":0.737},{"lat":-25,"lng":110,"u":-2.72,"v":-1.147},{"lat":-25,"lng":115,"u":-2.519,"v":-2.23},{"lat":-25,"lng":120,"u":-0.426,"v":-1.448},{"lat":-25,"lng":125,"u":-0.54,"v":-0.6},{"lat":-25,"lng":130,"u":-2.638,"v":-1.523},{"lat":-25,"lng":135,"u":-2.611,"v":-3.203},{"lat":-25,"lng":140,"u":-0.512,"v":-3.351},{"lat":-25,"lng":145,"u":-0.452,"v":-1.963},{"lat":-25,"lng":150,"u":-2.548,"v":-1.323},{"lat":-25,"lng":155,"u":-2.695,"v":-2.431},{"lat":-25,"lng":160,"u":-0.605,"v":-3.44},{"lat":-25,"lng":165,"u":-0.371,"v":-2.546},{"lat":-25,"lng":170,"u":-2.452,"v":-0.811},{"lat":-25,"lng":175,"u":-2.772,"v":-0.517},{"lat":-25,"lng":180,"u":-0.705,"v":-1.611},{"lat":-20,"lng":-180,"u":-3.949,"v":-2.02},{"lat":-20,"lng":-175,"u":-1.858,"v":-0.41},{"lat":-20,"lng":-170,"u":-2.004,"v":1.176},{"lat":-20,"lng":-165,"u":-4.1,"v":0.925},{"lat":-20,"lng":-160,"u":-4.042,"v":-0.106},{"lat":-20,"lng":-155,"u":-1.943,"v":0.338},{"lat":-20,"lng":-150,"u":-1.914,"v":2.168},{"lat":-20,"lng":-145,"u":-4.012,"v":3.073},{"lat":-20,"lng":-140,"u":-4.128,"v":2.111},{"lat":-20,"lng":-135,"u":-2.035,"v":1.168},{"lat":-20,"lng":-130,"u":-1.832,"v":1.999},{"lat":-20,"lng":-125,"u":-3.916,"v":3.479},{"lat":-20,"lng":-120,"u":-4.206,"v":3.354},{"lat":-20,"lng":-115,"u":-2.134,"v":1.761},{"lat":-20,"lng":-110,"u":-1.758,"v":1.016},{"lat":-20,"lng":-105,"u":-3.814,"v":1.999},{"lat":-20,"lng":-100,"u":-4.276,"v":2.793},{"lat":-20,"lng":-95,"u":-2.239,"v":1.685},{"lat":-20,"lng":-90,"u":-1.692,"v":-0.141},{"lat":-20,"lng":-85,"u":-3.707,"v":-0.437},{"lat":-20,"lng":-80,"u":-4.337,"v":0.614},{"lat":-20,"lng":-75,"u":-2.349,"v":0.706},{"lat":-20,"lng":-70,"u":-1.635,"v":-0.97},{"lat":-20,"lng":-65,"u":-3.594,"v":-2.441},{"lat":-20,"lng":-60,"u":-4.389,"v":-2.014},{"lat":-20,"lng":-55,"u":-2.463,"v":-0.903},{"lat":-20,"lng":-50,"u":-1.588,"v":-1.315},{"lat":-20,"lng":-45,"u":-3.478,"v":-2.989},{"lat":-20,"lng":-40,"u":-4.431,"v":-3.593},{"lat":-20,"lng":-35,"u":-2.582,"v":-2.355},{"lat":-20,"lng":-30,"u":-1.551,"v":-1.268},{"lat":-20,"lng":-25,"u":-3.358,"v":-1.971},{"lat":-20,"lng":-20,"u":-4.464,"v":-3.193},{"lat":-20,"lng":-15,"u":-2.703,"v":-2.744},{"lat":-20,"lng":-10,"u":-1.524,"v":-0.942},{"lat":-20,"lng":-5,"u":-3.236,"v":-0.13},{"lat":-20,"lng":0,"u":-4.486,"v":-1.03},{"lat":-20,"lng":5,"u":-2.826,"v":-1.631},{"lat":-20,"lng":10,"u":-1.507,"v":-0.35},{"lat":-20,"lng":15,"u":-3.112,"v":1.478},{"lat":-20,"lng":20,"u":-4.498,"v":1.662},{"lat":-20,"lng":25,"u":-2.95,"v":0.56},{"lat":-20,"lng":30,"u":-1.5,"v":0.498},{"lat":-20,"lng":35,"u":-2.987,"v":2.12},{"lat":-20,"lng":40,"u":-4.499,"v":3.364},{"lat":-20,"lng":45,"u":-3.075,"v":2.67},{"lat":-20,"lng":50,"u":-1.504,"v":1.404},{"lat":-20,"lng":55,"u":-2.863,"v":1.716},{"lat":-20,"lng":60,"u":-4.491,"v":3.177},{"lat":-20,"lng":65,"u":-3.199,"v":3.446},{"lat":-20,"lng":70,"u":-1.518,"v":1.931},{"lat":-20,"lng":75,"u":-2.739,"v":0.715},{"lat":-20,"lng":80,"u":-4.471,"v":1.316},{"lat":-20,"lng":85,"u":-3.322,"v":2.322},{"lat":-20,"lng":90,"u":-1.542,"v":1.616},{"lat":-20,"lng":95,"u":-2.617,"v":-0.305},{"lat":-20,"lng":100,"u":-4.442,"v":-1.084},{"lat":-20,"lng":105,"u":-3.443,"v":-0.17},{"lat":-20,"lng":110,"u":-1.576,"v":0.345},{"lat":-20,"lng":115,"u":-2.498,"v":-0.988},{"lat":-20,"lng":120,"u":-4.403,"v":-2.692},{"lat":-20,"lng":125,"u":-3.56,"v":-2.652},{"lat":-20,"lng":130,"u":-1.62,"v":-1.403},{"lat":-20,"lng":135,"u":-2.382,"v":-1.278},{"lat":-20,"lng":140,"u":-4.354,"v":-2.755},{"lat":-20,"lng":145,"u":-3.674,"v":-3.7},{"lat":-20,"lng":150,"u":-1.674,"v":-2.694},{"lat":-20,"lng":155,"u":-2.271,"v":-1.251},{"lat":-20,"lng":160,"u":-4.295,"v":-1.452},{"lat":-20,"lng":165,"u":-3.783,"v":-2.701},{"lat":-20,"lng":170,"u":-1.737,"v":-2.664},{"lat":-20,"lng":175,"u":-2.165,"v":-0.927},{"lat":-20,"lng":180,"u":-4.228,"v":0.343},{"lat":-15,"lng":-180,"u":-3.761,"v":-0.422},{"lat":-15,"lng":-175,"u":-5.653,"v":-1.319},{"lat":-15,"lng":-170,"u":-4.782,"v":-0.489},{"lat":-15,"lng":-165,"u":-2.855,"v":1.438},{"lat":-15,"lng":-160,"u":-3.645,"v":2.11},{"lat":-15,"lng":-155,"u":-5.606,"v":1.104},{"lat":-15,"lng":-150,"u":-4.897,"v":0.57},{"lat":-15,"lng":-145,"u":-2.907,"v":1.853},{"lat":-15,"lng":-140,"u":-3.533,"v":3.378},{"lat":-15,"lng":-135,"u":-5.549,"v":3.097},{"lat":-15,"lng":-130,"u":-5.007,"v":1.677},{"lat":-15,"lng":-125,"u":-2.968,"v":1.452},{"lat":-15,"lng":-120,"u":-3.425,"v":2.773},{"lat":-15,"lng":-115,"u":-5.483,"v":3.462},{"lat":-15,"lng":-110,"u":-5.111,"v":2.213},{"lat":-15,"lng":-105,"u":-3.038,"v":0.644},{"lat":-15,"lng":-100,"u":-3.324,"v":0.777},{"lat":-15,"lng":-95,"u":-5.409,"v":1.892},{"lat":-15,"lng":-90,"u":-5.21,"v":1.67},{"lat":-15,"lng":-85,"u":-3.117,"v":-0.17},{"lat":-15,"lng":-80,"u":-3.228,"v":-1.411},{"lat":-15,"lng":-75,"u":-5.327,"v":-0.782},{"lat":-15,"lng":-70,"u":-5.302,"v":0.077},{"lat":-15,"lng":-65,"u":-3.203,"v":-0.802},{"lat":-15,"lng":-60,"u":-3.14,"v":-2.625},{"lat":-15,"lng":-55,"u":-5.237,"v":-3.055},{"lat":-15,"lng":-50,"u":-5.386,"v":-1.85},{"lat":-15,"lng":-45,"u":-3.296,"v":-1.225},{"lat":-15,"lng":-40,"u":-3.059,"v":-2.385},{"lat":-15,"lng":-35,"u":-5.14,"v":-3.634},{"lat":-15,"lng":-30,"u":-5.463,"v":-3.021},{"lat":-15,"lng":-25,"u":-3.396,"v":-1.388},{"lat":-15,"lng":-20,"u":-2.987,"v":-1.057},{"lat":-15,"lng":-15,"u":-5.037,"v":-2.212},{"lat":-15,"lng":-10,"u":-5.531,"v":-2.619},{"lat":-15,"lng":-5,"u":-3.502,"v":-1.131},{"lat":-15,"lng":0,"u":-2.923,"v":0.505},{"lat":-15,"lng":5,"u":-4.928,"v":0.362},{"lat":-15,"lng":10,"u":-5.591,"v":-0.68},{"lat":-15,"lng":15,"u":-3.613,"v":-0.326},{"lat":-15,"lng":20,"u":-2.868,"v":1.529},{"lat":-15,"lng":25,"u":-4.815,"v":2.614},{"lat":-15,"lng":30,"u":-5.641,"v":1.812},{"lat":-15,"lng":35,"u":-3.728,"v":0.888},{"lat":-15,"lng":40,"u":-2.823,"v":1.713},{"lat":-15,"lng":45,"u":-4.698,"v":3.333},{"lat":-15,"lng":50,"u":-5.681,"v":3.445},{"lat":-15,"lng":55,"u":-3.847,"v":1.991},{"lat":-15,"lng":60,"u":-2.788,"v":1.241},{"lat":-15,"lng":65,"u":-4.578,"v":2.251},{"lat":-15,"lng":70,"u":-5.711,"v":3.216},{"lat":-15,"lng":75,"u":-3.969,"v":2.294},{"lat":-15,"lng":80,"u":-2.762,"v":0.497},{"lat":-15,"lng":85,"u":-4.455,"v":0.12},{"lat":-15,"lng":90,"u":-5.732,"v":1.174},{"lat":-15,"lng":95,"u":-4.092,"v":1.385},{"lat":-15,"lng":100,"u":-2.747,"v":-0.234},{"lat":-15,"lng":105,"u":-4.331,"v":-1.821},{"lat":-15,"lng":110,"u":-5.742,"v":-1.555},{"lat":-15,"lng":115,"u":-4.217,"v":-0.478},{"lat":-15,"lng":120,"u":-2.743,"v":-0.851},{"lat":-15,"lng":125,"u":-4.206,"v":-2.602},{"lat":-15,"lng":130,"u":-5.741,"v":-3.426},{"lat":-15,"lng":135,"u":-4.341,"v":-2.369},{"lat":-15,"lng":140,"u":-2.748,"v":-1.31},{"lat":-15,"lng":145,"u":-4.082,"v":-2.02},{"lat":-15,"lng":150,"u":-5.73,"v":-3.389},{"lat":-15,"lng":155,"u":-4.465,"v":-3.163},{"lat":-15,"lng":160,"u":-2.764,"v":-1.467},{"lat":-15,"lng":165,"u":-3.958,"v":-0.616},{"lat":-15,"lng":170,"u":-5.709,"v":-1.51},{"lat":-15,"lng":175,"u":-4.588,"v":-2.242},{"lat":-15,"lng":180,"u":-2.79,"v":-1.09},{"lat":-10,"lng":-180,"u":-5.148,"v":0.544},{"lat":-10,"lng":-175,"u":-3.696,"v":0.892},{"lat":-10,"lng":-170,"u":-5.182,"v":-0.153},{"lat":-10,"lng":-165,"u":-6.695,"v":-0.295},{"lat":-10,"lng":-160,"u":-5.273,"v":1.334},{"lat":-10,"lng":-155,"u":-3.7,"v":2.793},{"lat":-10,"lng":-150,"u":-5.057,"v":2.351},{"lat":-10,"lng":-145,"u":-6.686,"v":1.17},{"lat":-10,"lng":-140,"u":-5.397,"v":1.477},{"lat":-10,"lng":-135,"u":-3.714,"v":3.076},{"lat":-10,"lng":-130,"u":-4.933,"v":3.641},{"lat":-10,"lng":-125,"u":-6.667,"v":2.348},{"lat":-10,"lng":-120,"u":-5.52,"v":1.159},{"lat":-10,"lng":-115,"u":-3.739,"v":1.758},{"lat":-10,"lng":-110,"u":-4.812,"v":2.927},{"lat":-10,"lng":-105,"u":-6.638,"v":2.458},{"lat":-10,"lng":-100,"u":-5.641,"v":0.611},{"lat":-10,"lng":-95,"u":-3.773,"v":-0.276},{"lat":-10,"lng":-90,"u":-4.692,"v":0.578},{"lat":-10,"lng":-85,"u":-6.598,"v":1.194},{"lat":-10,"lng":-80,"u":-5.758,"v":-0.055},{"lat":-10,"lng":-75,"u":-3.817,"v":-1.883},{"lat":-10,"lng":-70,"u":-4.577,"v":-2.079},{"lat":-10,"lng":-65,"u":-6.549,"v":-0.942},{"lat":-10,"lng":-60,"u":-5.872,"v":-0.795},{"lat":-10,"lng":-55,"u":-3.871,"v":-2.339},{"lat":-10,"lng":-50,"u":-4.465,"v":-3.546},{"lat":-10,"lng":-45,"u":-6.491,"v":-2.812},{"lat":-10,"lng":-40,"u":-5.981,"v":-1.457},{"lat":-10,"lng":-35,"u":-3.934,"v":-1.655},{"lat":-10,"lng":-30,"u":-4.359,"v":-3.039},{"lat":-10,"lng":-25,"u":-6.423,"v":-3.274},{"lat":-10,"lng":-20,"u":-6.084,"v":-1.711},{"lat":-10,"lng":-15,"u":-4.006,"v":-0.408},{"lat":-10,"lng":-10,"u":-4.259,"v":-0.929},{"lat":-10,"lng":-5,"u":-6.347,"v":-1.913},{"lat":-10,"lng":0,"u":-6.182,"v":-1.218},{"lat":-10,"lng":5,"u":-4.086,"v":0.714},{"lat":-10,"lng":10,"u":-4.165,"v":1.531},{"lat":-10,"lng":15,"u":-6.263,"v":0.621},{"lat":-10,"lng":20,"u":-6.272,"v":0.05},{"lat":-10,"lng":25,"u":-4.174,"v":1.315},{"lat":-10,"lng":30,"u":-4.078,"v":2.987},{"lat":-10,"lng":35,"u":-6.172,"v":2.926},{"lat":-10,"lng":40,"u":-6.355,"v":1.611},{"lat":-10,"lng":45,"u":-4.268,"v":1.377},{"lat":-10,"lng":50,"u":-3.998,"v":2.763},{"lat":-10,"lng":55,"u":-6.074,"v":3.662},{"lat":-10,"lng":60,"u":-6.43,"v":2.612},{"lat":-10,"lng":65,"u":-4.37,"v":1.08},{"lat":-10,"lng":70,"u":-3.928,"v":1.178},{"lat":-10,"lng":75,"u":-5.97,"v":2.369},{"lat":-10,"lng":80,"u":-6.497,"v":2.321},{"lat":-10,"lng":85,"u":-4.476,"v":0.562},{"lat":-10,"lng":90,"u":-3.865,"v":-0.765},{"lat":-10,"lng":95,"u":-5.861,"v":-0.233},{"lat":-10,"lng":100,"u":-6.555,"v":0.664},{"lat":-10,"lng":105,"u":-4.588,"v":-0.142},{"lat":-10,"lng":110,"u":-3.813,"v":-2.035},{"lat":-10,"lng":115,"u":-5.746,"v":-2.664},{"lat":-10,"lng":120,"u":-6.603,"v":-1.593},{"lat":-10,"lng":125,"u":-4.704,"v":-0.967},{"lat":-10,"lng":130,"u":-3.769,"v":-2.146},{"lat":-10,"lng":135,"u":-5.629,"v":-3.572},{"lat":-10,"lng":140,"u":-6.641,"v":-3.189},{"lat":-10,"lng":145,"u":-4.824,"v":-1.654},{"lat":-10,"lng":150,"u":-3.736,"v":-1.306},{"lat":-10,"lng":155,"u":-5.508,"v":-2.516},{"lat":-10,"lng":160,"u":-6.67,"v":-3.112},{"lat":-10,"lng":165,"u":-4.946,"v":-1.78},{"lat":-10,"lng":170,"u":-3.712,"v":-0.129},{"lat":-10,"lng":175,"u":-5.385,"v":-0.191},{"lat":-10,"lng":180,"u":-6.688,"v":-1.264},{"lat":-5,"lng":-180,"u":-6.366,"v":-1.257},{"lat":-5,"lng":-175,"u":-7.194,"v":0.576},{"lat":-5,"lng":-170,"u":-5.283,"v":1.843},{"lat":-5,"lng":-165,"u":-4.375,"v":1.222},{"lat":-5,"lng":-160,"u":-6.249,"v":0.311},{"lat":-5,"lng":-155,"u":-7.235,"v":1.11},{"lat":-5,"lng":-150,"u":-5.402,"v":2.883},{"lat":-5,"lng":-145,"u":-4.34,"v":3.289},{"lat":-5,"lng":-140,"u":-6.129,"v":2.028},{"lat":-5,"lng":-135,"u":-7.265,"v":1.297},{"lat":-5,"lng":-130,"u":-5.524,"v":2.355},{"lat":-5,"lng":-125,"u":-4.315,"v":3.548},{"lat":-5,"lng":-120,"u":-6.006,"v":2.898},{"lat":-5,"lng":-115,"u":-7.285,"v":1.191},{"lat":-5,"lng":-110,"u":-5.647,"v":0.76},{"lat":-5,"lng":-105,"u":-4.3,"v":1.849},{"lat":-5,"lng":-100,"u":-5.882,"v":2.246},{"lat":-5,"lng":-95,"u":-7.295,"v":0.753},{"lat":-5,"lng":-90,"u":-5.772,"v":-0.925},{"lat":-5,"lng":-85,"u":-4.296,"v":-0.824},{"lat":-5,"lng":-80,"u":-5.757,"v":0.231},{"lat":-5,"lng":-75,"u":-7.294,"v":-0.066},{"lat":-5,"lng":-70,"u":-5.896,"v":-1.878},{"lat":-5,"lng":-65,"u":-4.301,"v":-2.953},{"lat":-5,"lng":-60,"u":-5.633,"v":-2.123},{"lat":-5,"lng":-55,"u":-7.283,"v":-1.114},{"lat":-5,"lng":-50,"u":-6.02,"v":-1.835},{"lat":-5,"lng":-45,"u":-4.317,"v":-3.389},{"lat":-5,"lng":-40,"u":-5.509,"v":-3.464},{"lat":-5,"lng":-35,"u":-7.262,"v":-1.943},{"lat":-5,"lng":-30,"u":-6.143,"v":-1.086},{"lat":-5,"lng":-25,"u":-4.344,"v":-2.003},{"lat":-5,"lng":-20,"u":-5.388,"v":-2.928},{"lat":-5,"lng":-15,"u":-7.23,"v":-1.987},{"lat":-5,"lng":-10,"u":-6.263,"v":-0.139},{"lat":-5,"lng":-5,"u":-4.38,"v":0.308},{"lat":-5,"lng":0,"u":-5.269,"v":-0.717},{"lat":-5,"lng":5,"u":-7.189,"v":-0.956},{"lat":-5,"lng":10,"u":-6.38,"v":0.632},{"lat":-5,"lng":15,"u":-4.426,"v":2.224},{"lat":-5,"lng":20,"u":-5.154,"v":1.96},{"lat":-5,"lng":25,"u":-7.138,"v":0.831},{"lat":-5,"lng":30,"u":-6.492,"v":1.111},{"lat":-5,"lng":35,"u":-4.482,"v":2.793},{"lat":-5,"lng":40,"u":-5.044,"v":3.582},{"lat":-5,"lng":45,"u":-7.078,"v":2.475},{"lat":-5,"lng":50,"u":-6.6,"v":1.316},{"lat":-5,"lng":55,"u":-4.547,"v":1.916},{"lat":-5,"lng":60,"u":-4.939,"v":3.221},{"lat":-5,"lng":65,"u":-7.009,"v":2.965},{"lat":-5,"lng":70,"u":-6.703,"v":1.214},{"lat":-5,"lng":75,"u":-4.62,"v":0.274},{"lat":-5,"lng":80,"u":-4.839,"v":1.102},{"lat":-5,"lng":85,"u":-6.931,"v":1.827},{"lat":-5,"lng":90,"u":-6.799,"v":0.689},{"lat":-5,"lng":95,"u":-4.702,"v":-1.192},{"lat":-5,"lng":100,"u":-4.747,"v":-1.545},{"lat":-5,"lng":105,"u":-6.846,"v":-0.476},{"lat":-5,"lng":110,"u":-6.888,"v":-0.282},{"lat":-5,"lng":115,"u":-4.791,"v":-1.844},{"lat":-5,"lng":120,"u":-4.661,"v":-3.233},{"lat":-5,"lng":125,"u":-6.753,"v":-2.709},{"lat":-5,"lng":130,"u":-6.97,"v":-1.424},{"lat":-5,"lng":135,"u":-4.887,"v":-1.613},{"lat":-5,"lng":140,"u":-4.584,"v":-3.097},{"lat":-5,"lng":145,"u":-6.654,"v":-3.558},{"lat":-5,"lng":150,"u":-7.043,"v":-2.16},{"lat":-5,"lng":155,"u":-4.989,"v":-0.858},{"lat":-5,"lng":160,"u":-4.514,"v":-1.353},{"lat":-5,"lng":165,"u":-6.549,"v":-2.442},{"lat":-5,"lng":170,"u":-7.108,"v":-1.913},{"lat":-5,"lng":175,"u":-5.097,"v":-0.014},{"lat":-5,"lng":180,"u":-4.454,"v":0.916},{"lat":0,"lng":-180,"u":-4.979,"v":-0.113},{"lat":0,"lng":-175,"u":-4.88,"v":-0.756},{"lat":0,"lng":-170,"u":-6.974,"v":0.447},{"lat":0,"lng":-165,"u":-7.16,"v":2.262},{"lat":0,"lng":-160,"u":-5.074,"v":2.458},{"lat":0,"lng":-155,"u":-4.801,"v":1.276},{"lat":0,"lng":-150,"u":-6.876,"v":1.034},{"lat":0,"lng":-145,"u":-7.235,"v":2.493},{"lat":0,"lng":-140,"u":-5.175,"v":3.656},{"lat":0,"lng":-135,"u":-4.73,"v":2.879},{"lat":0,"lng":-130,"u":-6.772,"v":1.434},{"lat":0,"lng":-125,"u":-7.302,"v":1.52},{"lat":0,"lng":-120,"u":-5.282,"v":2.829},{"lat":0,"lng":-115,"u":-4.668,"v":3.036},{"lat":0,"lng":-110,"u":-6.663,"v":1.433},{"lat":0,"lng":-105,"u":-7.359,"v":0.053},{"lat":0,"lng":-100,"u":-5.394,"v":0.504},{"lat":0,"lng":-95,"u":-4.616,"v":1.477},{"lat":0,"lng":-90,"u":-6.548,"v":0.807},{"lat":0,"lng":-85,"u":-7.407,"v":-1.123},{"lat":0,"lng":-80,"u":-5.51,"v":-1.964},{"lat":0,"lng":-75,"u":-4.572,"v":-1.047},{"lat":0,"lng":-70,"u":-6.431,"v":-0.408},{"lat":0,"lng":-65,"u":-7.446,"v":-1.594},{"lat":0,"lng":-60,"u":-5.63,"v":-3.223},{"lat":0,"lng":-55,"u":-4.539,"v":-3.134},{"lat":0,"lng":-50,"u":-6.31,"v":-1.748},{"lat":0,"lng":-45,"u":-7.474,"v":-1.403},{"lat":0,"lng":-40,"u":-5.752,"v":-2.695},{"lat":0,"lng":-35,"u":-4.516,"v":-3.549},{"lat":0,"lng":-30,"u":-6.187,"v":-2.457},{"lat":0,"lng":-25,"u":-7.492,"v":-0.844},{"lat":0,"lng":-20,"u":-5.875,"v":-0.845},{"lat":0,"lng":-15,"u":-4.503,"v":-1.988},{"lat":0,"lng":-10,"u":-6.062,"v":-1.94},{"lat":0,"lng":-5,"u":-7.5,"v":-0.171},{"lat":0,"lng":0,"u":-6,"v":1.2},{"lat":0,"lng":5,"u":-4.5,"v":0.697},{"lat":0,"lng":10,"u":-5.938,"v":-0.23},{"lat":0,"lng":15,"u":-7.497,"v":0.512},{"lat":0,"lng":20,"u":-6.125,"v":2.369},{"lat":0,"lng":25,"u":-4.508,"v":2.987},{"lat":0,"lng":30,"u":-5.813,"v":1.873},{"lat":0,"lng":35,"u":-7.484,"v":1.15},{"lat":0,"lng":40,"u":-6.248,"v":2.229},{"lat":0,"lng":45,"u":-4.526,"v":3.597},{"lat":0,"lng":50,"u":-5.69,"v":3.176},{"lat":0,"lng":55,"u":-7.461,"v":1.564},{"lat":0,"lng":60,"u":-6.37,"v":1.107},{"lat":0,"lng":65,"u":-4.554,"v":2.237},{"lat":0,"lng":70,"u":-5.569,"v":2.805},{"lat":0,"lng":75,"u":-7.428,"v":1.453},{"lat":0,"lng":80,"u":-6.49,"v":-0.254},{"lat":0,"lng":85,"u":-4.593,"v":-0.255},{"lat":0,"lng":90,"u":-5.452,"v":0.807},{"lat":0,"lng":95,"u":-7.384,"v":0.609},{"lat":0,"lng":100,"u":-6.606,"v":-1.206},{"lat":0,"lng":105,"u":-4.641,"v":-2.447},{"lat":0,"lng":110,"u":-5.337,"v":-1.781},{"lat":0,"lng":115,"u":-7.332,"v":-0.795},{"lat":0,"lng":120,"u":-6.718,"v":-1.501},{"lat":0,"lng":125,"u":-4.698,"v":-3.179},{"lat":0,"lng":130,"u":-5.228,"v":-3.49},{"lat":0,"lng":135,"u":-7.27,"v":-2.121},{"lat":0,"lng":140,"u":-6.825,"v":-1.268},{"lat":0,"lng":145,"u":-4.765,"v":-2.206},{"lat":0,"lng":150,"u":-5.124,"v":-3.296},{"lat":0,"lng":155,"u":-7.199,"v":-2.554},{"lat":0,"lng":160,"u":-6.926,"v":-0.756},{"lat":0,"lng":165,"u":-4.84,"v":-0.238},{"lat":0,"lng":170,"u":-5.026,"v":-1.263},{"lat":0,"lng":175,"u":-7.12,"v":-1.625},{"lat":0,"lng":180,"u":-7.021,"v":-0.113},{"lat":5,"lng":-180,"u":-7.137,"v":1.351},{"lat":5,"lng":-175,"u":-6.494,"v":1.28},{"lat":5,"lng":-170,"u":-4.483,"v":0.2},{"lat":5,"lng":-165,"u":-5.042,"v":0.426},{"lat":5,"lng":-160,"u":-7.077,"v":2.183},{"lat":5,"lng":-155,"u":-6.602,"v":3.237},{"lat":5,"lng":-150,"u":-4.548,"v":2.372},{"lat":5,"lng":-145,"u":-4.937,"v":1.272},{"lat":5,"lng":-140,"u":-7.008,"v":1.884},{"lat":5,"lng":-135,"u":-6.704,"v":3.368},{"lat":5,"lng":-130,"u":-4.621,"v":3.406},{"lat":5,"lng":-125,"u":-4.838,"v":1.823},{"lat":5,"lng":-120,"u":-6.93,"v":0.863},{"lat":5,"lng":-115,"u":-6.8,"v":1.692},{"lat":5,"lng":-110,"u":-4.703,"v":2.586},{"lat":5,"lng":-105,"u":-4.745,"v":1.637},{"lat":5,"lng":-100,"u":-6.844,"v":-0.251},{"lat":5,"lng":-95,"u":-6.889,"v":-0.756},{"lat":5,"lng":-90,"u":-4.792,"v":0.253},{"lat":5,"lng":-85,"u":-4.66,"v":0.533},{"lat":5,"lng":-80,"u":-6.752,"v":-1.011},{"lat":5,"lng":-75,"u":-6.971,"v":-2.594},{"lat":5,"lng":-70,"u":-4.888,"v":-2.322},{"lat":5,"lng":-65,"u":-4.582,"v":-1.13},{"lat":5,"lng":-60,"u":-6.652,"v":-1.31},{"lat":5,"lng":-55,"u":-7.044,"v":-2.914},{"lat":5,"lng":-50,"u":-4.991,"v":-3.665},{"lat":5,"lng":-45,"u":-4.513,"v":-2.506},{"lat":5,"lng":-40,"u":-6.547,"v":-1.247},{"lat":5,"lng":-35,"u":-7.109,"v":-1.739},{"lat":5,"lng":-30,"u":-5.099,"v":-2.985},{"lat":5,"lng":-25,"u":-4.453,"v":-2.705},{"lat":5,"lng":-20,"u":-6.437,"v":-0.908},{"lat":5,"lng":-15,"u":-7.165,"v":0.111},{"lat":5,"lng":-10,"u":-5.211,"v":-0.662},{"lat":5,"lng":-5,"u":-4.402,"v":-1.392},{"lat":5,"lng":0,"u":-6.322,"v":-0.281},{"lat":5,"lng":5,"u":-7.211,"v":1.602},{"lat":5,"lng":10,"u":-5.328,"v":1.974},{"lat":5,"lng":15,"u":-4.361,"v":0.881},{"lat":5,"lng":20,"u":-6.203,"v":0.608},{"lat":5,"lng":25,"u":-7.247,"v":2.093},{"lat":5,"lng":30,"u":-5.448,"v":3.446},{"lat":5,"lng":35,"u":-4.329,"v":2.887},{"lat":5,"lng":40,"u":-6.082,"v":1.517},{"lat":5,"lng":45,"u":-7.274,"v":1.592},{"lat":5,"lng":50,"u":-5.571,"v":2.995},{"lat":5,"lng":55,"u":-4.308,"v":3.418},{"lat":5,"lng":60,"u":-5.959,"v":1.973},{"lat":5,"lng":65,"u":-7.29,"v":0.583},{"lat":5,"lng":70,"u":-5.695,"v":0.99},{"lat":5,"lng":75,"u":-4.297,"v":2.047},{"lat":5,"lng":80,"u":-5.834,"v":1.525},{"lat":5,"lng":85,"u":-7.296,"v":-0.388},{"lat":5,"lng":90,"u":-5.819,"v":-1.361},{"lat":5,"lng":95,"u":-4.297,"v":-0.542},{"lat":5,"lng":100,"u":-5.709,"v":0.133},{"lat":5,"lng":105,"u":-7.291,"v":-1.018},{"lat":5,"lng":110,"u":-5.944,"v":-2.775},{"lat":5,"lng":115,"u":-4.306,"v":-2.905},{"lat":5,"lng":120,"u":-5.585,"v":-1.634},{"lat":5,"lng":125,"u":-7.276,"v":-1.281},{"lat":5,"lng":130,"u":-6.067,"v":-2.626},{"lat":5,"lng":135,"u":-4.326,"v":-3.684},{"lat":5,"lng":140,"u":-5.463,"v":-2.802},{"lat":5,"lng":145,"u":-7.251,"v":-1.242},{"lat":5,"lng":150,"u":-6.189,"v":-1.213},{"lat":5,"lng":155,"u":-4.357,"v":-2.425},{"lat":5,"lng":160,"u":-5.342,"v":-2.557},{"lat":5,"lng":165,"u":-7.216,"v":-0.891},{"lat":5,"lng":170,"u":-6.308,"v":0.549},{"lat":5,"lng":175,"u":-4.397,"v":0.14},{"lat":5,"lng":180,"u":-5.225,"v":-0.821},{"lat":10,"lng":-180,"u":-3.704,"v":-0.396},{"lat":10,"lng":-175,"u":-5.007,"v":1.519},{"lat":10,"lng":-170,"u":-6.68,"v":2.371},{"lat":10,"lng":-165,"u":-5.447,"v":1.434},{"lat":10,"lng":-160,"u":-3.723,"v":0.719},{"lat":10,"lng":-155,"u":-4.884,"v":1.814},{"lat":10,"lng":-150,"u":-6.657,"v":3.392},{"lat":10,"lng":-145,"u":-5.569,"v":3.27},{"lat":10,"lng":-140,"u":-3.751,"v":1.811},{"lat":10,"lng":-135,"u":-4.764,"v":1.352},{"lat":10,"lng":-130,"u":-6.623,"v":2.552},{"lat":10,"lng":-125,"u":-5.688,"v":3.364},{"lat":10,"lng":-120,"u":-3.79,"v":2.237},{"lat":10,"lng":-115,"u":-4.646,"v":0.55},{"lat":10,"lng":-110,"u":-6.58,"v":0.465},{"lat":10,"lng":-105,"u":-5.804,"v":1.569},{"lat":10,"lng":-100,"u":-3.838,"v":1.532},{"lat":10,"lng":-95,"u":-4.532,"v":-0.233},{"lat":10,"lng":-90,"u":-6.527,"v":-1.634},{"lat":10,"lng":-85,"u":-5.916,"v":-1.148},{"lat":10,"lng":-80,"u":-3.895,"v":-0.179},{"lat":10,"lng":-75,"u":-4.422,"v":-0.845},{"lat":10,"lng":-70,"u":-6.465,"v":-2.653},{"lat":10,"lng":-65,"u":-6.023,"v":-3.25},{"lat":10,"lng":-60,"u":-3.962,"v":-2.087},{"lat":10,"lng":-55,"u":-4.318,"v":-1.262},{"lat":10,"lng":-50,"u":-6.394,"v":-2.237},{"lat":10,"lng":-45,"u":-6.124,"v":-3.547},{"lat":10,"lng":-40,"u":-4.037,"v":-3.088},{"lat":10,"lng":-35,"u":-4.22,"v":-1.404},{"lat":10,"lng":-30,"u":-6.315,"v":-0.843},{"lat":10,"lng":-25,"u":-6.219,"v":-1.899},{"lat":10,"lng":-20,"u":-4.12,"v":-2.45},{"lat":10,"lng":-15,"u":-4.129,"v":-1.089},{"lat":10,"lng":-10,"u":-6.228,"v":0.663},{"lat":10,"lng":-5,"u":-6.306,"v":0.714},{"lat":10,"lng":0,"u":-4.211,"v":-0.35},{"lat":10,"lng":5,"u":-4.045,"v":-0.203},{"lat":10,"lng":10,"u":-6.134,"v":1.571},{"lat":10,"lng":15,"u":-6.386,"v":2.805},{"lat":10,"lng":20,"u":-4.308,"v":2.119},{"lat":10,"lng":25,"u":-3.969,"v":1.056},{"lat":10,"lng":30,"u":-6.033,"v":1.659},{"lat":10,"lng":35,"u":-6.458,"v":3.269},{"lat":10,"lng":40,"u":-4.412,"v":3.543},{"lat":10,"lng":45,"u":-3.902,"v":2.112},{"lat":10,"lng":50,"u":-5.927,"v":1.153},{"lat":10,"lng":55,"u":-6.521,"v":1.991},{"lat":10,"lng":60,"u":-4.52,"v":3.035},{"lat":10,"lng":65,"u":-3.843,"v":2.272},{"lat":10,"lng":70,"u":-5.816,"v":0.421},{"lat":10,"lng":75,"u":-6.575,"v":-0.173},{"lat":10,"lng":80,"u":-4.634,"v":0.813},{"lat":10,"lng":85,"u":-3.794,"v":1.194},{"lat":10,"lng":90,"u":-5.7,"v":-0.29},{"lat":10,"lng":95,"u":-6.619,"v":-1.986},{"lat":10,"lng":100,"u":-4.752,"v":-1.889},{"lat":10,"lng":105,"u":-3.755,"v":-0.756},{"lat":10,"lng":110,"u":-5.581,"v":-0.903},{"lat":10,"lng":115,"u":-6.654,"v":-2.573},{"lat":10,"lng":120,"u":-4.872,"v":-3.54},{"lat":10,"lng":125,"u":-3.725,"v":-2.576},{"lat":10,"lng":130,"u":-5.459,"v":-1.359},{"lat":10,"lng":135,"u":-6.678,"v":-1.848},{"lat":10,"lng":140,"u":-4.995,"v":-3.221},{"lat":10,"lng":145,"u":-3.706,"v":-3.161},{"lat":10,"lng":150,"u":-5.335,"v":-1.479},{"lat":10,"lng":155,"u":-6.692,"v":-0.421},{"lat":10,"lng":160,"u":-5.119,"v":-1.166},{"lat":10,"lng":165,"u":-3.697,"v":-2.005},{"lat":10,"lng":170,"u":-5.211,"v":-1.022},{"lat":10,"lng":175,"u":-6.696,"v":0.892},{"lat":10,"lng":180,"u":-5.244,"v":1.412},{"lat":15,"lng":-180,"u":-5.695,"v":0.204},{"lat":15,"lng":-175,"u":-3.897,"v":-0.129},{"lat":15,"lng":-170,"u":-2.776,"v":1.358},{"lat":15,"lng":-165,"u":-4.527,"v":2.92},{"lat":15,"lng":-160,"u":-5.721,"v":2.629},{"lat":15,"lng":-155,"u":-4.02,"v":1.368},{"lat":15,"lng":-150,"u":-2.755,"v":1.441},{"lat":15,"lng":-145,"u":-4.404,"v":2.961},{"lat":15,"lng":-140,"u":-5.737,"v":3.671},{"lat":15,"lng":-135,"u":-4.144,"v":2.461},{"lat":15,"lng":-130,"u":-2.744,"v":1.106},{"lat":15,"lng":-125,"u":-4.279,"v":1.494},{"lat":15,"lng":-120,"u":-5.743,"v":2.685},{"lat":15,"lng":-115,"u":-4.269,"v":2.39},{"lat":15,"lng":-110,"u":-2.744,"v":0.558},{"lat":15,"lng":-105,"u":-4.154,"v":-0.527},{"lat":15,"lng":-100,"u":-5.738,"v":0.202},{"lat":15,"lng":-95,"u":-4.393,"v":0.949},{"lat":15,"lng":-90,"u":-2.754,"v":-0.12},{"lat":15,"lng":-85,"u":-4.03,"v":-1.993},{"lat":15,"lng":-80,"u":-5.723,"v":-2.371},{"lat":15,"lng":-75,"u":-4.517,"v":-1.242},{"lat":15,"lng":-70,"u":-2.774,"v":-0.88},{"lat":15,"lng":-65,"u":-3.908,"v":-2.28},{"lat":15,"lng":-60,"u":-5.697,"v":-3.589},{"lat":15,"lng":-55,"u":-4.638,"v":-2.99},{"lat":15,"lng":-50,"u":-2.804,"v":-1.536},{"lat":15,"lng":-45,"u":-3.787,"v":-1.497},{"lat":15,"lng":-40,"u":-5.662,"v":-2.819},{"lat":15,"lng":-35,"u":-4.757,"v":-3.208},{"lat":15,"lng":-30,"u":-2.845,"v":-1.723},{"lat":15,"lng":-25,"u":-3.67,"v":-0.254},{"lat":15,"lng":-20,"u":-5.617,"v":-0.584},{"lat":15,"lng":-15,"u":-4.872,"v":-1.62},{"lat":15,"lng":-10,"u":-2.895,"v":-1.116},{"lat":15,"lng":-5,"u":-3.557,"v":0.797},{"lat":15,"lng":0,"u":-5.562,"v":1.799},{"lat":15,"lng":5,"u":-4.983,"v":0.982},{"lat":15,"lng":10,"u":-2.954,"v":0.249},{"lat":15,"lng":15,"u":-3.448,"v":1.324},{"lat":15,"lng":20,"u":-5.498,"v":3.038},{"lat":15,"lng":25,"u":-5.089,"v":3.144},{"lat":15,"lng":30,"u":-3.022,"v":1.809},{"lat":15,"lng":35,"u":-3.345,"v":1.347},{"lat":15,"lng":40,"u":-5.426,"v":2.595},{"lat":15,"lng":45,"u":-5.189,"v":3.604},{"lat":15,"lng":50,"u":-3.099,"v":2.682},{"lat":15,"lng":55,"u":-3.249,"v":1.041},{"lat":15,"lng":60,"u":-5.345,"v":0.911},{"lat":15,"lng":65,"u":-5.282,"v":2.066},{"lat":15,"lng":70,"u":-3.183,"v":2.19},{"lat":15,"lng":75,"u":-3.159,"v":0.512},{"lat":15,"lng":80,"u":-5.257,"v":-0.975},{"lat":15,"lng":85,"u":-5.369,"v":-0.605},{"lat":15,"lng":90,"u":-3.275,"v":0.376},{"lat":15,"lng":95,"u":-3.076,"v":-0.221},{"lat":15,"lng":100,"u":-5.161,"v":-2.091},{"lat":15,"lng":105,"u":-5.447,"v":-2.891},{"lat":15,"lng":110,"u":-3.374,"v":-1.883},{"lat":15,"lng":115,"u":-3.002,"v":-1.07},{"lat":15,"lng":120,"u":-5.06,"v":-2.056},{"lat":15,"lng":125,"u":-5.517,"v":-3.529},{"lat":15,"lng":130,"u":-3.479,"v":-3.304},{"lat":15,"lng":135,"u":-2.936,"v":-1.732},{"lat":15,"lng":140,"u":-4.952,"v":-1.153},{"lat":15,"lng":145,"u":-5.579,"v":-2.243},{"lat":15,"lng":150,"u":-3.588,"v":-2.966},{"lat":15,"lng":155,"u":-2.88,"v":-1.764},{"lat":15,"lng":160,"u":-4.84,"v":-0.003},{"lat":15,"lng":165,"u":-5.631,"v":0.144},{"lat":15,"lng":170,"u":-3.703,"v":-0.925},{"lat":15,"lng":175,"u":-2.832,"v":-0.883},{"lat":15,"lng":180,"u":-4.724,"v":0.872},{"lat":20,"lng":-180,"u":-1.772,"v":2.053},{"lat":20,"lng":-175,"u":-3.835,"v":1.573},{"lat":20,"lng":-170,"u":-4.263,"v":0.55},{"lat":20,"lng":-165,"u":-2.217,"v":1.13},{"lat":20,"lng":-160,"u":-1.705,"v":2.878},{"lat":20,"lng":-155,"u":-3.729,"v":3.447},{"lat":20,"lng":-150,"u":-4.326,"v":2.23},{"lat":20,"lng":-145,"u":-2.326,"v":1.3},{"lat":20,"lng":-140,"u":-1.646,"v":2.169},{"lat":20,"lng":-135,"u":-3.618,"v":3.42},{"lat":20,"lng":-130,"u":-4.38,"v":2.928},{"lat":20,"lng":-125,"u":-2.44,"v":1.178},{"lat":20,"lng":-120,"u":-1.597,"v":0.522},{"lat":20,"lng":-115,"u":-3.502,"v":1.512},{"lat":20,"lng":-110,"u":-4.424,"v":2.055},{"lat":20,"lng":-105,"u":-2.557,"v":0.698},{"lat":20,"lng":-100,"u":-1.558,"v":-1.084},{"lat":20,"lng":-95,"u":-3.383,"v":-1.173},{"lat":20,"lng":-90,"u":-4.458,"v":-0.094},{"lat":20,"lng":-85,"u":-2.678,"v":-0.178},{"lat":20,"lng":-80,"u":-1.529,"v":-1.898},{"lat":20,"lng":-75,"u":-3.261,"v":-3.115},{"lat":20,"lng":-70,"u":-4.482,"v":-2.399},{"lat":20,"lng":-65,"u":-2.801,"v":-1.252},{"lat":20,"lng":-60,"u":-1.509,"v":-1.747},{"lat":20,"lng":-55,"u":-3.137,"v":-3.284},{"lat":20,"lng":-50,"u":-4.496,"v":-3.52},{"lat":20,"lng":-45,"u":-2.925,"v":-2.029},{"lat":20,"lng":-40,"u":-1.501,"v":-0.967},{"lat":20,"lng":-35,"u":-3.013,"v":-1.711},{"lat":20,"lng":-30,"u":-4.5,"v":-2.716},{"lat":20,"lng":-25,"u":-3.05,"v":-1.94},{"lat":20,"lng":-20,"u":-1.502,"v":-0.048},{"lat":20,"lng":-15,"u":-2.888,"v":0.609},{"lat":20,"lng":-10,"u":-4.493,"v":-0.35},{"lat":20,"lng":-5,"u":-3.174,"v":-0.763},{"lat":20,"lng":0,"u":-1.514,"v":0.68},{"lat":20,"lng":5,"u":-2.764,"v":2.37},{"lat":20,"lng":10,"u":-4.476,"v":2.272},{"lat":20,"lng":15,"u":-3.297,"v":1.086},{"lat":20,"lng":20,"u":-1.536,"v":1.137},{"lat":20,"lng":25,"u":-2.642,"v":2.728},{"lat":20,"lng":30,"u":-4.449,"v":3.656},{"lat":20,"lng":35,"u":-3.418,"v":2.645},{"lat":20,"lng":40,"u":-1.569,"v":1.331},{"lat":20,"lng":45,"u":-2.522,"v":1.709},{"lat":20,"lng":50,"u":-4.412,"v":3.015},{"lat":20,"lng":55,"u":-3.537,"v":2.927},{"lat":20,"lng":60,"u":-1.611,"v":1.2},{"lat":20,"lng":65,"u":-2.406,"v":0.059},{"lat":20,"lng":70,"u":-4.365,"v":0.741},{"lat":20,"lng":75,"u":-3.651,"v":1.575},{"lat":20,"lng":80,"u":-1.663,"v":0.614},{"lat":20,"lng":85,"u":-2.293,"v":-1.306},{"lat":20,"lng":90,"u":-4.308,"v":-1.851},{"lat":20,"lng":95,"u":-3.761,"v":-0.815},{"lat":20,"lng":100,"u":-1.724,"v":-0.421},{"lat":20,"lng":105,"u":-2.186,"v":-1.831},{"lat":20,"lng":110,"u":-4.242,"v":-3.315},{"lat":20,"lng":115,"u":-3.866,"v":-2.937},{"lat":20,"lng":120,"u":-1.794,"v":-1.57},{"lat":20,"lng":125,"u":-2.084,"v":-1.521},{"lat":20,"lng":130,"u":-4.168,"v":-2.925},{"lat":20,"lng":135,"u":-3.965,"v":-3.531},{"lat":20,"lng":140,"u":-1.872,"v":-2.219},{"lat":20,"lng":145,"u":-1.988,"v":-0.757},{"lat":20,"lng":150,"u":-4.086,"v":-1.046},{"lat":20,"lng":155,"u":-4.057,"v":-2.162},{"lat":20,"lng":160,"u":-1.958,"v":-1.816},{"lat":20,"lng":165,"u":-1.9,"v":0.057},{"lat":20,"lng":170,"u":-3.996,"v":1.176},{"lat":20,"lng":175,"u":-4.142,"v":0.458},{"lat":20,"lng":180,"u":-2.051,"v":-0.31},{"lat":25,"lng":-180,"u":-2.401,"v":0.502},{"lat":25,"lng":-175,"u":-0.334,"v":2.351},{"lat":25,"lng":-170,"u":-0.654,"v":2.724},{"lat":25,"lng":-165,"u":-2.735,"v":1.55},{"lat":25,"lng":-160,"u":-2.501,"v":1.091},{"lat":25,"lng":-155,"u":-0.41,"v":2.398},{"lat":25,"lng":-150,"u":-0.557,"v":3.658},{"lat":25,"lng":-145,"u":-2.654,"v":3.018},{"lat":25,"lng":-140,"u":-2.594,"v":1.479},{"lat":25,"lng":-135,"u":-0.495,"v":1.328},{"lat":25,"lng":-130,"u":-0.468,"v":2.573},{"lat":25,"lng":-125,"u":-2.566,"v":2.936},{"lat":25,"lng":-120,"u":-2.68,"v":1.42},{"lat":25,"lng":-115,"u":-0.587,"v":-0.117},{"lat":25,"lng":-110,"u":-0.385,"v":0.147},{"lat":25,"lng":-105,"u":-2.47,"v":1.173},{"lat":25,"lng":-100,"u":-2.759,"v":0.701},{"lat":25,"lng":-95,"u":-0.686,"v":-1.199},{"lat":25,"lng":-90,"u":-0.311,"v":-2.217},{"lat":25,"lng":-85,"u":-2.368,"v":-1.39},{"lat":25,"lng":-80,"u":-2.829,"v":-0.588},{"lat":25,"lng":-75,"u":-0.79,"v":-1.575},{"lat":25,"lng":-70,"u":-0.246,"v":-3.238},{"lat":25,"lng":-65,"u":-2.261,"v":-3.314},{"lat":25,"lng":-60,"u":-2.89,"v":-1.911},{"lat":25,"lng":-55,"u":-0.9,"v":-1.338},{"lat":25,"lng":-50,"u":-0.189,"v":-2.489},{"lat":25,"lng":-45,"u":-2.149,"v":-3.451},{"lat":25,"lng":-40,"u":-2.942,"v":-2.493},{"lat":25,"lng":-35,"u":-1.015,"v":-0.778},{"lat":25,"lng":-30,"u":-0.142,"v":-0.556},{"lat":25,"lng":-25,"u":-2.032,"v":-1.662},{"lat":25,"lng":-20,"u":-2.984,"v":-1.791},{"lat":25,"lng":-15,"u":-1.133,"v":-0.113},{"lat":25,"lng":-10,"u":-0.104,"v":1.407},{"lat":25,"lng":-5,"u":-1.912,"v":1.064},{"lat":25,"lng":0,"u":-3.016,"v":0.05},{"lat":25,"lng":5,"u":-1.254,"v":0.576},{"lat":25,"lng":10,"u":-0.077,"v":2.399},{"lat":25,"lng":15,"u":-1.79,"v":3.182},{"lat":25,"lng":20,"u":-3.039,"v":2.131},{"lat":25,"lng":25,"u":-1.377,"v":1.222},{"lat":25,"lng":30,"u":-0.06,"v":2.103},{"lat":25,"lng":35,"u":-1.666,"v":3.514},{"lat":25,"lng":40,"u":-3.051,"v":3.251},{"lat":25,"lng":45,"u":-1.502,"v":1.609},{"lat":25,"lng":50,"u":-0.053,"v":0.924},{"lat":25,"lng":55,"u":-1.542,"v":1.932},{"lat":25,"lng":60,"u":-3.052,"v":2.63},{"lat":25,"lng":65,"u":-1.627,"v":1.416},{"lat":25,"lng":70,"u":-0.057,"v":-0.391},{"lat":25,"lng":75,"u":-1.417,"v":-0.596},{"lat":25,"lng":80,"u":-3.044,"v":0.464},{"lat":25,"lng":85,"u":-1.751,"v":0.466},{"lat":25,"lng":90,"u":-0.07,"v":-1.251},{"lat":25,"lng":95,"u":-1.293,"v":-2.632},{"lat":25,"lng":100,"u":-3.025,"v":-2.098},{"lat":25,"lng":105,"u":-1.874,"v":-0.995},{"lat":25,"lng":110,"u":-0.095,"v":-1.474},{"lat":25,"lng":115,"u":-1.172,"v":-3.121},{"lat":25,"lng":120,"u":-2.995,"v":-3.592},{"lat":25,"lng":125,"u":-1.994,"v":-2.266},{"lat":25,"lng":130,"u":-0.129,"v":-1.215},{"lat":25,"lng":135,"u":-1.052,"v":-1.965},{"lat":25,"lng":140,"u":-2.956,"v":-3.115},{"lat":25,"lng":145,"u":-2.112,"v":-2.536},{"lat":25,"lng":150,"u":-0.173,"v":-0.703},{"lat":25,"lng":155,"u":-0.937,"v":0.032},{"lat":25,"lng":160,"u":-2.907,"v":-0.901},{"lat":25,"lng":165,"u":-2.226,"v":-1.418},{"lat":25,"lng":170,"u":-0.226,"v":-0.054},{"lat":25,"lng":175,"u":-0.825,"v":1.728},{"lat":25,"lng":180,"u":-2.849,"v":1.802},{"lat":30,"lng":-180,"u":0.36,"v":0.513},{"lat":30,"lng":-175,"u":-1.448,"v":0.521},{"lat":30,"lng":-170,"u":-0.42,"v":2.176},{"lat":30,"lng":-165,"u":1.431,"v":3.365},{"lat":30,"lng":-160,"u":0.48,"v":2.614},{"lat":30,"lng":-155,"u":-1.411,"v":1.378},{"lat":30,"lng":-150,"u":-0.539,"v":1.761},{"lat":30,"lng":-145,"u":1.388,"v":3.222},{"lat":30,"lng":-140,"u":0.596,"v":3.422},{"lat":30,"lng":-135,"u":-1.364,"v":1.874},{"lat":30,"lng":-130,"u":-0.653,"v":0.715},{"lat":30,"lng":-125,"u":1.337,"v":1.372},{"lat":30,"lng":-120,"u":0.709,"v":2.347},{"lat":30,"lng":-115,"u":-1.307,"v":1.57},{"lat":30,"lng":-110,"u":-0.763,"v":-0.349},{"lat":30,"lng":-105,"u":1.275,"v":-1.058},{"lat":30,"lng":-100,"u":0.816,"v":-0.114},{"lat":30,"lng":-95,"u":-1.241,"v":0.344},{"lat":30,"lng":-90,"u":-0.868,"v":-1.045},{"lat":30,"lng":-85,"u":1.205,"v":-2.716},{"lat":30,"lng":-80,"u":0.918,"v":-2.606},{"lat":30,"lng":-75,"u":-1.167,"v":-1.359},{"lat":30,"lng":-70,"u":-0.966,"v":-1.305},{"lat":30,"lng":-65,"u":1.127,"v":-2.811},{"lat":30,"lng":-60,"u":1.013,"v":-3.697},{"lat":30,"lng":-55,"u":-1.085,"v":-2.637},{"lat":30,"lng":-50,"u":-1.058,"v":-1.229},{"lat":30,"lng":-45,"u":1.041,"v":-1.499},{"lat":30,"lng":-40,"u":1.102,"v":-2.744},{"lat":30,"lng":-35,"u":-0.995,"v":-2.636},{"lat":30,"lng":-30,"u":-1.143,"v":-0.872},{"lat":30,"lng":-25,"u":0.947,"v":0.339},{"lat":30,"lng":-20,"u":1.182,"v":-0.289},{"lat":30,"lng":-15,"u":-0.898,"v":-1.13},{"lat":30,"lng":-10,"u":-1.22,"v":-0.206},{"lat":30,"lng":-5,"u":0.848,"v":1.705},{"lat":30,"lng":0,"u":1.255,"v":2.263},{"lat":30,"lng":5,"u":-0.795,"v":1.2},{"lat":30,"lng":10,"u":-1.288,"v":0.724},{"lat":30,"lng":15,"u":0.742,"v":2.05},{"lat":30,"lng":20,"u":1.319,"v":3.49},{"lat":30,"lng":25,"u":-0.687,"v":3.077},{"lat":30,"lng":30,"u":-1.347,"v":1.629},{"lat":30,"lng":35,"u":0.631,"v":1.466},{"lat":30,"lng":40,"u":1.374,"v":2.784},{"lat":30,"lng":45,"u":-0.574,"v":3.352},{"lat":30,"lng":50,"u":-1.398,"v":2},{"lat":30,"lng":55,"u":0.516,"v":0.458},{"lat":30,"lng":60,"u":1.419,"v":0.662},{"lat":30,"lng":65,"u":-0.457,"v":1.747},{"lat":30,"lng":70,"u":-1.438,"v":1.413},{"lat":30,"lng":75,"u":0.397,"v":-0.463},{"lat":30,"lng":80,"u":1.455,"v":-1.616},{"lat":30,"lng":85,"u":-0.336,"v":-0.91},{"lat":30,"lng":90,"u":-1.468,"v":-0.092},{"lat":30,"lng":95,"u":0.275,"v":-1.045},{"lat":30,"lng":100,"u":1.48,"v":-2.827},{"lat":30,"lng":105,"u":-0.214,"v":-3.126},{"lat":30,"lng":110,"u":-1.489,"v":-1.859},{"lat":30,"lng":115,"u":0.152,"v":-1.286},{"lat":30,"lng":120,"u":1.495,"v":-2.476},{"lat":30,"lng":125,"u":-0.09,"v":-3.627},{"lat":30,"lng":130,"u":-1.499,"v":-2.884},{"lat":30,"lng":135,"u":0.027,"v":-1.234},{"lat":30,"lng":140,"u":1.5,"v":-0.972},{"lat":30,"lng":145,"u":0.035,"v":-2.125},{"lat":30,"lng":150,"u":-1.499,"v":-2.42},{"lat":30,"lng":155,"u":-0.097,"v":-0.849},{"lat":30,"lng":160,"u":1.494,"v":0.738},{"lat":30,"lng":165,"u":0.16,"v":0.508},{"lat":30,"lng":170,"u":-1.488,"v":-0.516},{"lat":30,"lng":175,"u":-0.222,"v":-0.069},{"lat":30,"lng":180,"u":1.479,"v":1.795},{"lat":35,"lng":-180,"u":4.174,"v":2.602},{"lat":35,"lng":-175,"u":5.493,"v":1.754},{"lat":35,"lng":-170,"u":3.889,"v":0.874},{"lat":35,"lng":-165,"u":2.502,"v":1.765},{"lat":35,"lng":-160,"u":4.049,"v":3.369},{"lat":35,"lng":-155,"u":5.5,"v":3.409},{"lat":35,"lng":-150,"u":4.013,"v":1.939},{"lat":35,"lng":-145,"u":2.501,"v":1.254},{"lat":35,"lng":-140,"u":3.924,"v":2.309},{"lat":35,"lng":-135,"u":5.496,"v":3.228},{"lat":35,"lng":-130,"u":4.138,"v":2.241},{"lat":35,"lng":-125,"u":2.51,"v":0.462},{"lat":35,"lng":-120,"u":3.8,"v":0.157},{"lat":35,"lng":-115,"u":5.482,"v":1.226},{"lat":35,"lng":-110,"u":4.261,"v":1.37},{"lat":35,"lng":-105,"u":2.529,"v":-0.292},{"lat":35,"lng":-100,"u":3.677,"v":-1.832},{"lat":35,"lng":-95,"u":5.458,"v":-1.502},{"lat":35,"lng":-90,"u":4.383,"v":-0.444},{"lat":35,"lng":-85,"u":2.558,"v":-0.889},{"lat":35,"lng":-80,"u":3.557,"v":-2.653},{"lat":35,"lng":-75,"u":5.423,"v":-3.409},{"lat":35,"lng":-70,"u":4.502,"v":-2.311},{"lat":35,"lng":-65,"u":2.597,"v":-1.301},{"lat":35,"lng":-60,"u":3.439,"v":-2.074},{"lat":35,"lng":-55,"u":5.379,"v":-3.421},{"lat":35,"lng":-50,"u":4.618,"v":-3.124},{"lat":35,"lng":-45,"u":2.646,"v":-1.417},{"lat":35,"lng":-40,"u":3.326,"v":-0.634},{"lat":35,"lng":-35,"u":5.325,"v":-1.568},{"lat":35,"lng":-30,"u":4.73,"v":-2.249},{"lat":35,"lng":-25,"u":2.705,"v":-1.035},{"lat":35,"lng":-20,"u":3.217,"v":0.805},{"lat":35,"lng":-15,"u":5.263,"v":1.054},{"lat":35,"lng":-10,"u":4.836,"v":-0.009},{"lat":35,"lng":-5,"u":2.772,"v":-0.067},{"lat":35,"lng":0,"u":3.113,"v":1.598},{"lat":35,"lng":5,"u":5.191,"v":2.964},{"lat":35,"lng":10,"u":4.937,"v":2.408},{"lat":35,"lng":15,"u":2.848,"v":1.228},{"lat":35,"lng":20,"u":3.016,"v":1.6},{"lat":35,"lng":25,"u":5.111,"v":3.172},{"lat":35,"lng":30,"u":5.031,"v":3.603},{"lat":35,"lng":35,"u":2.932,"v":2.221},{"lat":35,"lng":40,"u":2.925,"v":1.068},{"lat":35,"lng":45,"u":5.023,"v":1.717},{"lat":35,"lng":50,"u":5.118,"v":2.821},{"lat":35,"lng":55,"u":3.023,"v":2.226},{"lat":35,"lng":60,"u":2.842,"v":0.35},{"lat":35,"lng":65,"u":4.929,"v":-0.454},{"lat":35,"lng":70,"u":5.197,"v":0.442},{"lat":35,"lng":75,"u":3.121,"v":0.981},{"lat":35,"lng":80,"u":2.767,"v":-0.346},{"lat":35,"lng":85,"u":4.828,"v":-2.124},{"lat":35,"lng":90,"u":5.268,"v":-2.203},{"lat":35,"lng":95,"u":3.225,"v":-1.037},{"lat":35,"lng":100,"u":2.7,"v":-0.959},{"lat":35,"lng":105,"u":4.721,"v":-2.519},{"lat":35,"lng":110,"u":5.33,"v":-3.615},{"lat":35,"lng":115,"u":3.334,"v":-2.763},{"lat":35,"lng":120,"u":2.642,"v":-1.41},{"lat":35,"lng":125,"u":4.609,"v":-1.669},{"lat":35,"lng":130,"u":5.383,"v":-3.02},{"lat":35,"lng":135,"u":3.448,"v":-3.124},{"lat":35,"lng":140,"u":2.594,"v":-1.485},{"lat":35,"lng":145,"u":4.493,"v":-0.234},{"lat":35,"lng":150,"u":5.427,"v":-0.814},{"lat":35,"lng":155,"u":3.566,"v":-1.741},{"lat":35,"lng":160,"u":2.555,"v":-0.939},{"lat":35,"lng":165,"u":4.374,"v":0.995},{"lat":35,"lng":170,"u":5.46,"v":1.709},{"lat":35,"lng":175,"u":3.687,"v":0.744},{"lat":35,"lng":180,"u":2.527,"v":0.235},{"lat":40,"lng":-180,"u":6.243,"v":1.372},{"lat":40,"lng":-175,"u":5.58,"v":3.012},{"lat":40,"lng":-170,"u":7.557,"v":2.881},{"lat":40,"lng":-165,"u":8.303,"v":1.566},{"lat":40,"lng":-160,"u":6.356,"v":1.403},{"lat":40,"lng":-155,"u":5.53,"v":2.819},{"lat":40,"lng":-150,"u":7.442,"v":3.661},{"lat":40,"lng":-145,"u":8.348,"v":2.555},{"lat":40,"lng":-140,"u":6.474,"v":1.057},{"lat":40,"lng":-135,"u":5.49,"v":1.224},{"lat":40,"lng":-130,"u":7.323,"v":2.413},{"lat":40,"lng":-125,"u":8.383,"v":2.294},{"lat":40,"lng":-120,"u":6.594,"v":0.507},{"lat":40,"lng":-115,"u":5.459,"v":-0.763},{"lat":40,"lng":-110,"u":7.201,"v":-0.176},{"lat":40,"lng":-105,"u":8.408,"v":0.686},{"lat":40,"lng":-100,"u":6.717,"v":-0.189},{"lat":40,"lng":-95,"u":5.439,"v":-2.078},{"lat":40,"lng":-90,"u":7.078,"v":-2.636},{"lat":40,"lng":-85,"u":8.424,"v":-1.538},{"lat":40,"lng":-80,"u":6.841,"v":-0.971},{"lat":40,"lng":-75,"u":5.429,"v":-2.204},{"lat":40,"lng":-70,"u":6.953,"v":-3.592},{"lat":40,"lng":-65,"u":8.428,"v":-3.141},{"lat":40,"lng":-60,"u":6.965,"v":-1.612},{"lat":40,"lng":-55,"u":5.43,"v":-1.336},{"lat":40,"lng":-50,"u":6.829,"v":-2.571},{"lat":40,"lng":-45,"u":8.423,"v":-3.106},{"lat":40,"lng":-40,"u":7.09,"v":-1.723},{"lat":40,"lng":-35,"u":5.441,"v":-0.11},{"lat":40,"lng":-30,"u":6.705,"v":-0.24},{"lat":40,"lng":-25,"u":8.406,"v":-1.305},{"lat":40,"lng":-20,"u":7.213,"v":-0.996},{"lat":40,"lng":-15,"u":5.462,"v":0.868},{"lat":40,"lng":-10,"u":6.582,"v":2.042},{"lat":40,"lng":-5,"u":8.38,"v":1.335},{"lat":40,"lng":0,"u":7.335,"v":0.458},{"lat":40,"lng":5,"u":5.493,"v":1.326},{"lat":40,"lng":10,"u":6.462,"v":3.056},{"lat":40,"lng":15,"u":8.344,"v":3.328},{"lat":40,"lng":20,"u":7.453,"v":2},{"lat":40,"lng":25,"u":5.534,"v":1.318},{"lat":40,"lng":30,"u":6.345,"v":2.407},{"lat":40,"lng":35,"u":8.298,"v":3.507},{"lat":40,"lng":40,"u":7.568,"v":2.727},{"lat":40,"lng":45,"u":5.585,"v":1.004},{"lat":40,"lng":50,"u":6.232,"v":0.646},{"lat":40,"lng":55,"u":8.242,"v":1.74},{"lat":40,"lng":60,"u":7.679,"v":2.031},{"lat":40,"lng":65,"u":5.645,"v":0.459},{"lat":40,"lng":70,"u":6.124,"v":-1.165},{"lat":40,"lng":75,"u":8.178,"v":-0.969},{"lat":40,"lng":80,"u":7.784,"v":0.076},{"lat":40,"lng":85,"u":5.714,"v":-0.307},{"lat":40,"lng":90,"u":6.022,"v":-2.125},{"lat":40,"lng":95,"u":8.104,"v":-3.085},{"lat":40,"lng":100,"u":7.883,"v":-2.16},{"lat":40,"lng":105,"u":5.792,"v":-1.177},{"lat":40,"lng":110,"u":5.926,"v":-1.954},{"lat":40,"lng":115,"u":8.023,"v":-3.449},{"lat":40,"lng":120,"u":7.976,"v":-3.386},{"lat":40,"lng":125,"u":5.877,"v":-1.804},{"lat":40,"lng":130,"u":5.837,"v":-1.003},{"lat":40,"lng":135,"u":7.934,"v":-1.951},{"lat":40,"lng":140,"u":8.062,"v":-2.785},{"lat":40,"lng":145,"u":5.97,"v":-1.73},{"lat":40,"lng":150,"u":5.755,"v":0.113},{"lat":40,"lng":155,"u":7.838,"v":0.47},{"lat":40,"lng":160,"u":8.139,"v":-0.572},{"lat":40,"lng":165,"u":6.069,"v":-0.721},{"lat":40,"lng":170,"u":5.681,"v":0.921},{"lat":40,"lng":175,"u":7.736,"v":2.434},{"lat":40,"lng":180,"u":8.209,"v":2.06},{"lat":45,"lng":-180,"u":9.11,"v":0.796},{"lat":45,"lng":-175,"u":9.032,"v":1.148},{"lat":45,"lng":-170,"u":6.933,"v":2.844},{"lat":45,"lng":-165,"u":6.924,"v":3.567},{"lat":45,"lng":-160,"u":9.022,"v":2.417},{"lat":45,"lng":-155,"u":9.119,"v":1.306},{"lat":45,"lng":-150,"u":7.025,"v":1.969},{"lat":45,"lng":-145,"u":6.84,"v":3.255},{"lat":45,"lng":-140,"u":8.927,"v":2.927},{"lat":45,"lng":-135,"u":9.198,"v":1.163},{"lat":45,"lng":-130,"u":7.123,"v":0.29},{"lat":45,"lng":-125,"u":6.765,"v":1.16},{"lat":45,"lng":-120,"u":8.826,"v":1.836},{"lat":45,"lng":-115,"u":9.269,"v":0.635},{"lat":45,"lng":-110,"u":7.227,"v":-1.224},{"lat":45,"lng":-105,"u":6.699,"v":-1.505},{"lat":45,"lng":-100,"u":8.719,"v":-0.426},{"lat":45,"lng":-95,"u":9.331,"v":-0.3},{"lat":45,"lng":-90,"u":7.336,"v":-1.901},{"lat":45,"lng":-85,"u":6.641,"v":-3.241},{"lat":45,"lng":-80,"u":8.607,"v":-2.655},{"lat":45,"lng":-75,"u":9.384,"v":-1.392},{"lat":45,"lng":-70,"u":7.45,"v":-1.654},{"lat":45,"lng":-65,"u":6.593,"v":-3.146},{"lat":45,"lng":-60,"u":8.491,"v":-3.539},{"lat":45,"lng":-55,"u":9.427,"v":-2.102},{"lat":45,"lng":-50,"u":7.568,"v":-0.852},{"lat":45,"lng":-45,"u":6.555,"v":-1.408},{"lat":45,"lng":-40,"u":8.372,"v":-2.472},{"lat":45,"lng":-35,"u":9.461,"v":-1.871},{"lat":45,"lng":-30,"u":7.689,"v":0.034},{"lat":45,"lng":-25,"u":6.526,"v":0.895},{"lat":45,"lng":-20,"u":8.25,"v":0.024},{"lat":45,"lng":-15,"u":9.484,"v":-0.551},{"lat":45,"lng":-10,"u":7.812,"v":0.725},{"lat":45,"lng":-5,"u":6.508,"v":2.487},{"lat":45,"lng":0,"u":8.126,"v":2.56},{"lat":45,"lng":5,"u":9.497,"v":1.342},{"lat":45,"lng":10,"u":7.936,"v":1.164},{"lat":45,"lng":15,"u":6.5,"v":2.638},{"lat":45,"lng":20,"u":8.001,"v":3.69},{"lat":45,"lng":25,"u":9.5,"v":2.793},{"lat":45,"lng":30,"u":8.061,"v":1.348},{"lat":45,"lng":35,"u":6.503,"v":1.496},{"lat":45,"lng":40,"u":7.877,"v":2.778},{"lat":45,"lng":45,"u":9.492,"v":2.857},{"lat":45,"lng":50,"u":8.185,"v":1.181},{"lat":45,"lng":55,"u":6.516,"v":-0.143},{"lat":45,"lng":60,"u":7.753,"v":0.374},{"lat":45,"lng":65,"u":9.474,"v":1.298},{"lat":45,"lng":70,"u":8.308,"v":0.528},{"lat":45,"lng":75,"u":6.539,"v":-1.401},{"lat":45,"lng":80,"u":7.631,"v":-2.133},{"lat":45,"lng":85,"u":9.446,"v":-1.151},{"lat":45,"lng":90,"u":8.429,"v":-0.568},{"lat":45,"lng":95,"u":6.572,"v":-1.805},{"lat":45,"lng":100,"u":7.511,"v":-3.359},{"lat":45,"lng":105,"u":9.408,"v":-3.137},{"lat":45,"lng":110,"u":8.547,"v":-1.713},{"lat":45,"lng":115,"u":6.615,"v":-1.428},{"lat":45,"lng":120,"u":7.395,"v":-2.727},{"lat":45,"lng":125,"u":9.36,"v":-3.465},{"lat":45,"lng":130,"u":8.661,"v":-2.261},{"lat":45,"lng":135,"u":6.668,"v":-0.662},{"lat":45,"lng":140,"u":7.283,"v":-0.736},{"lat":45,"lng":145,"u":9.302,"v":-1.856},{"lat":45,"lng":150,"u":8.771,"v":-1.695},{"lat":45,"lng":155,"u":6.73,"v":0.123},{"lat":45,"lng":160,"u":7.176,"v":1.415},{"lat":45,"lng":165,"u":9.236,"v":0.831},{"lat":45,"lng":170,"u":8.875,"v":-0.06},{"lat":45,"lng":175,"u":6.8,"v":0.761},{"lat":45,"lng":180,"u":7.075,"v":2.59},{"lat":50,"lng":-180,"u":5.535,"v":2.959},{"lat":50,"lng":-175,"u":6.343,"v":1.817},{"lat":50,"lng":-170,"u":8.297,"v":1.152},{"lat":50,"lng":-165,"u":7.57,"v":2.286},{"lat":50,"lng":-160,"u":5.586,"v":3.62},{"lat":50,"lng":-155,"u":6.231,"v":3.129},{"lat":50,"lng":-150,"u":8.241,"v":1.522},{"lat":50,"lng":-145,"u":7.68,"v":1.136},{"lat":50,"lng":-140,"u":5.646,"v":2.292},{"lat":50,"lng":-135,"u":6.123,"v":2.801},{"lat":50,"lng":-130,"u":8.177,"v":1.396},{"lat":50,"lng":-125,"u":7.786,"v":-0.275},{"lat":50,"lng":-120,"u":5.715,"v":-0.207},{"lat":50,"lng":-115,"u":6.02,"v":0.849},{"lat":50,"lng":-110,"u":8.103,"v":0.579},{"lat":50,"lng":-105,"u":7.885,"v":-1.261},{"lat":50,"lng":-100,"u":5.793,"v":-2.441},{"lat":50,"lng":-95,"u":5.924,"v":-1.723},{"lat":50,"lng":-90,"u":8.022,"v":-0.775},{"lat":50,"lng":-85,"u":7.978,"v":-1.55},{"lat":50,"lng":-80,"u":5.878,"v":-3.22},{"lat":50,"lng":-75,"u":5.835,"v":-3.459},{"lat":50,"lng":-70,"u":7.933,"v":-2.066},{"lat":50,"lng":-65,"u":8.063,"v":-1.275},{"lat":50,"lng":-60,"u":5.971,"v":-2.263},{"lat":50,"lng":-55,"u":5.754,"v":-3.314},{"lat":50,"lng":-50,"u":7.837,"v":-2.504},{"lat":50,"lng":-45,"u":8.141,"v":-0.716},{"lat":50,"lng":-40,"u":6.07,"v":-0.271},{"lat":50,"lng":-35,"u":5.68,"v":-1.317},{"lat":50,"lng":-30,"u":7.734,"v":-1.616},{"lat":50,"lng":-25,"u":8.21,"v":-0.056},{"lat":50,"lng":-20,"u":6.176,"v":1.592},{"lat":50,"lng":-15,"u":5.615,"v":1.418},{"lat":50,"lng":-10,"u":7.626,"v":0.339},{"lat":50,"lng":-5,"u":8.27,"v":0.645},{"lat":50,"lng":0,"u":6.286,"v":2.405},{"lat":50,"lng":5,"u":5.56,"v":3.341},{"lat":50,"lng":10,"u":7.514,"v":2.375},{"lat":50,"lng":15,"u":8.321,"v":1.297},{"lat":50,"lng":20,"u":6.401,"v":1.964},{"lat":50,"lng":25,"u":5.513,"v":3.392},{"lat":50,"lng":30,"u":7.397,"v":3.293},{"lat":50,"lng":35,"u":8.363,"v":1.648},{"lat":50,"lng":40,"u":6.519,"v":0.745},{"lat":50,"lng":45,"u":5.477,"v":1.612},{"lat":50,"lng":50,"u":7.277,"v":2.422},{"lat":50,"lng":55,"u":8.394,"v":1.364},{"lat":50,"lng":60,"u":6.641,"v":-0.515},{"lat":50,"lng":65,"u":5.45,"v":-0.924},{"lat":50,"lng":70,"u":7.154,"v":0.11},{"lat":50,"lng":75,"u":8.415,"v":0.308},{"lat":50,"lng":80,"u":6.764,"v":-1.285},{"lat":50,"lng":85,"u":5.434,"v":-2.785},{"lat":50,"lng":90,"u":7.03,"v":-2.396},{"lat":50,"lng":95,"u":8.427,"v":-1.198},{"lat":50,"lng":100,"u":6.888,"v":-1.445},{"lat":50,"lng":105,"u":5.428,"v":-3.033},{"lat":50,"lng":110,"u":6.906,"v":-3.655},{"lat":50,"lng":115,"u":8.427,"v":-2.397},{"lat":50,"lng":120,"u":7.013,"v":-1.166},{"lat":50,"lng":125,"u":5.433,"v":-1.712},{"lat":50,"lng":130,"u":6.781,"v":-2.9},{"lat":50,"lng":135,"u":8.418,"v":-2.491},{"lat":50,"lng":140,"u":7.137,"v":-0.652},{"lat":50,"lng":145,"u":5.448,"v":0.291},{"lat":50,"lng":150,"u":6.658,"v":-0.53},{"lat":50,"lng":155,"u":8.398,"v":-1.188},{"lat":50,"lng":160,"u":7.26,"v":0.009},{"lat":50,"lng":165,"u":5.473,"v":1.857},{"lat":50,"lng":170,"u":6.536,"v":2.114},{"lat":50,"lng":175,"u":8.368,"v":0.983},{"lat":50,"lng":180,"u":7.38,"v":0.778},{"lat":55,"lng":-180,"u":5.5,"v":2.151},{"lat":55,"lng":-175,"u":4.063,"v":3.455},{"lat":55,"lng":-170,"u":2.503,"v":2.833},{"lat":55,"lng":-165,"u":3.875,"v":1.484},{"lat":55,"lng":-160,"u":5.492,"v":1.632},{"lat":55,"lng":-155,"u":4.187,"v":3.045},{"lat":55,"lng":-150,"u":2.516,"v":3.4},{"lat":55,"lng":-145,"u":3.751,"v":1.915},{"lat":55,"lng":-140,"u":5.474,"v":0.575},{"lat":55,"lng":-135,"u":4.31,"v":1.044},{"lat":55,"lng":-130,"u":2.539,"v":2.079},{"lat":55,"lng":-125,"u":3.629,"v":1.484},{"lat":55,"lng":-120,"u":5.445,"v":-0.438},{"lat":55,"lng":-115,"u":4.431,"v":-1.342},{"lat":55,"lng":-110,"u":2.573,"v":-0.484},{"lat":55,"lng":-105,"u":3.509,"v":0.139},{"lat":55,"lng":-100,"u":5.407,"v":-1.073},{"lat":55,"lng":-95,"u":4.549,"v":-2.805},{"lat":55,"lng":-90,"u":2.616,"v":-2.863},{"lat":55,"lng":-85,"u":3.393,"v":-1.585},{"lat":55,"lng":-80,"u":5.359,"v":-1.301},{"lat":55,"lng":-75,"u":4.663,"v":-2.683},{"lat":55,"lng":-70,"u":2.669,"v":-3.688},{"lat":55,"lng":-65,"u":3.281,"v":-2.747},{"lat":55,"lng":-60,"u":5.301,"v":-1.213},{"lat":55,"lng":-55,"u":4.773,"v":-1.255},{"lat":55,"lng":-50,"u":2.731,"v":-2.473},{"lat":55,"lng":-45,"u":3.175,"v":-2.536},{"lat":55,"lng":-40,"u":5.235,"v":-0.834},{"lat":55,"lng":-35,"u":4.877,"v":0.552},{"lat":55,"lng":-30,"u":2.801,"v":0.085},{"lat":55,"lng":-25,"u":3.073,"v":-0.849},{"lat":55,"lng":-20,"u":5.16,"v":-0.123},{"lat":55,"lng":-15,"u":4.975,"v":1.786},{"lat":55,"lng":-10,"u":2.881,"v":2.523},{"lat":55,"lng":-5,"u":2.979,"v":1.515},{"lat":55,"lng":0,"u":5.077,"v":0.848},{"lat":55,"lng":5,"u":5.066,"v":1.993},{"lat":55,"lng":10,"u":2.967,"v":3.495},{"lat":55,"lng":15,"u":2.891,"v":3.237},{"lat":55,"lng":20,"u":4.986,"v":1.737},{"lat":55,"lng":25,"u":5.15,"v":1.338},{"lat":55,"lng":30,"u":3.061,"v":2.548},{"lat":55,"lng":35,"u":2.811,"v":3.248},{"lat":55,"lng":40,"u":4.889,"v":2.011},{"lat":55,"lng":45,"u":5.226,"v":0.341},{"lat":55,"lng":50,"u":3.162,"v":0.334},{"lat":55,"lng":55,"u":2.739,"v":1.424},{"lat":55,"lng":60,"u":4.786,"v":1.281},{"lat":55,"lng":65,"u":5.294,"v":-0.529},{"lat":55,"lng":70,"u":3.268,"v":-1.846},{"lat":55,"lng":75,"u":2.676,"v":-1.27},{"lat":55,"lng":80,"u":4.677,"v":-0.329},{"lat":55,"lng":85,"u":5.352,"v":-1.07},{"lat":55,"lng":90,"u":3.379,"v":-2.847},{"lat":55,"lng":95,"u":2.622,"v":-3.314},{"lat":55,"lng":100,"u":4.563,"v":-2.074},{"lat":55,"lng":105,"u":5.402,"v":-1.293},{"lat":55,"lng":110,"u":3.495,"v":-2.306},{"lat":55,"lng":115,"u":2.577,"v":-3.532},{"lat":55,"lng":120,"u":4.446,"v":-2.939},{"lat":55,"lng":125,"u":5.441,"v":-1.226},{"lat":55,"lng":130,"u":3.614,"v":-0.735},{"lat":55,"lng":135,"u":2.543,"v":-1.803},{"lat":55,"lng":140,"u":4.325,"v":-2.251},{"lat":55,"lng":145,"u":5.471,"v":-0.801},{"lat":55,"lng":150,"u":3.736,"v":0.91},{"lat":55,"lng":155,"u":2.518,"v":0.866},{"lat":55,"lng":160,"u":4.202,"v":-0.197},{"lat":55,"lng":165,"u":5.49,"v":0.039},{"lat":55,"lng":170,"u":3.859,"v":1.832},{"lat":55,"lng":175,"u":2.504,"v":2.96},{"lat":55,"lng":180,"u":4.078,"v":2.172},{"lat":60,"lng":-180,"u":2.584,"v":1.035},{"lat":60,"lng":-175,"u":4.467,"v":1.708},{"lat":60,"lng":-170,"u":5.435,"v":3.311},{"lat":60,"lng":-165,"u":3.593,"v":3.513},{"lat":60,"lng":-160,"u":2.548,"v":2.057},{"lat":60,"lng":-155,"u":4.347,"v":1.158},{"lat":60,"lng":-150,"u":5.466,"v":2.048},{"lat":60,"lng":-145,"u":3.714,"v":3.055},{"lat":60,"lng":-140,"u":2.522,"v":2.223},{"lat":60,"lng":-135,"u":4.224,"v":0.38},{"lat":60,"lng":-130,"u":5.487,"v":-0.142},{"lat":60,"lng":-125,"u":3.838,"v":0.867},{"lat":60,"lng":-120,"u":2.506,"v":1.187},{"lat":60,"lng":-115,"u":4.1,"v":-0.348},{"lat":60,"lng":-110,"u":5.498,"v":-2.004},{"lat":60,"lng":-105,"u":3.962,"v":-1.84},{"lat":60,"lng":-100,"u":2.5,"v":-0.716},{"lat":60,"lng":-95,"u":3.975,"v":-0.935},{"lat":60,"lng":-90,"u":5.499,"v":-2.626},{"lat":60,"lng":-85,"u":4.087,"v":-3.531},{"lat":60,"lng":-80,"u":2.505,"v":-2.518},{"lat":60,"lng":-75,"u":3.851,"v":-1.343},{"lat":60,"lng":-70,"u":5.489,"v":-1.899},{"lat":60,"lng":-65,"u":4.211,"v":-3.26},{"lat":60,"lng":-60,"u":2.52,"v":-3.127},{"lat":60,"lng":-55,"u":3.727,"v":-1.426},{"lat":60,"lng":-50,"u":5.469,"v":-0.431},{"lat":60,"lng":-45,"u":4.334,"v":-1.224},{"lat":60,"lng":-40,"u":2.545,"v":-2.02},{"lat":60,"lng":-35,"u":3.606,"v":-0.97},{"lat":60,"lng":-30,"u":5.439,"v":0.93},{"lat":60,"lng":-25,"u":4.454,"v":1.378},{"lat":60,"lng":-20,"u":2.58,"v":0.338},{"lat":60,"lng":-15,"u":3.487,"v":0.08},{"lat":60,"lng":-10,"u":5.399,"v":1.611},{"lat":60,"lng":-5,"u":4.571,"v":3.087},{"lat":60,"lng":0,"u":2.625,"v":2.674},{"lat":60,"lng":5,"u":3.372,"v":1.4},{"lat":60,"lng":10,"u":5.349,"v":1.537},{"lat":60,"lng":15,"u":4.685,"v":3.044},{"lat":60,"lng":20,"u":2.68,"v":3.625},{"lat":60,"lng":25,"u":3.261,"v":2.315},{"lat":60,"lng":30,"u":5.289,"v":0.987},{"lat":60,"lng":35,"u":4.793,"v":1.434},{"lat":60,"lng":40,"u":2.744,"v":2.574},{"lat":60,"lng":45,"u":3.155,"v":2.155},{"lat":60,"lng":50,"u":5.221,"v":0.284},{"lat":60,"lng":55,"u":4.896,"v":-0.721},{"lat":60,"lng":60,"u":2.816,"v":0.065},{"lat":60,"lng":65,"u":3.055,"v":0.749},{"lat":60,"lng":70,"u":5.145,"v":-0.401},{"lat":60,"lng":75,"u":4.993,"v":-2.235},{"lat":60,"lng":80,"u":2.897,"v":-2.492},{"lat":60,"lng":85,"u":2.961,"v":-1.318},{"lat":60,"lng":90,"u":5.06,"v":-1.019},{"lat":60,"lng":95,"u":5.083,"v":-2.444},{"lat":60,"lng":100,"u":2.985,"v":-3.65},{"lat":60,"lng":105,"u":2.875,"v":-2.925},{"lat":60,"lng":110,"u":4.968,"v":-1.46},{"lat":60,"lng":115,"u":5.165,"v":-1.485},{"lat":60,"lng":120,"u":3.08,"v":-2.788},{"lat":60,"lng":125,"u":2.796,"v":-3.052},{"lat":60,"lng":130,"u":4.87,"v":-1.482},{"lat":60,"lng":135,"u":5.24,"v":-0.058},{"lat":60,"lng":140,"u":3.182,"v":-0.458},{"lat":60,"lng":145,"u":2.726,"v":-1.452},{"lat":60,"lng":150,"u":4.765,"v":-0.843},{"lat":60,"lng":155,"u":5.306,"v":1.083},{"lat":60,"lng":160,"u":3.289,"v":1.982},{"lat":60,"lng":165,"u":2.665,"v":1.095},{"lat":60,"lng":170,"u":4.655,"v":0.412},{"lat":60,"lng":175,"u":5.363,"v":1.547},{"lat":60,"lng":180,"u":3.401,"v":3.199},{"lat":65,"lng":-180,"u":3.152,"v":3.103},{"lat":65,"lng":-175,"u":1.063,"v":1.76},{"lat":65,"lng":-170,"u":0.809,"v":1.366},{"lat":65,"lng":-165,"u":2.888,"v":2.653},{"lat":65,"lng":-160,"u":3.227,"v":3.61},{"lat":65,"lng":-155,"u":1.163,"v":2.627},{"lat":65,"lng":-150,"u":0.738,"v":1.01},{"lat":65,"lng":-145,"u":2.784,"v":0.952},{"lat":65,"lng":-140,"u":3.295,"v":2.114},{"lat":65,"lng":-135,"u":1.27,"v":2.17},{"lat":65,"lng":-130,"u":0.675,"v":0.455},{"lat":65,"lng":-125,"u":2.675,"v":-0.98},{"lat":65,"lng":-120,"u":3.353,"v":-0.55},{"lat":65,"lng":-115,"u":1.381,"v":0.405},{"lat":65,"lng":-110,"u":0.621,"v":-0.263},{"lat":65,"lng":-105,"u":2.561,"v":-2.139},{"lat":65,"lng":-100,"u":3.402,"v":-2.87},{"lat":65,"lng":-95,"u":1.497,"v":-1.826},{"lat":65,"lng":-90,"u":0.577,"v":-1.066},{"lat":65,"lng":-85,"u":2.444,"v":-2.112},{"lat":65,"lng":-80,"u":3.442,"v":-3.557},{"lat":65,"lng":-75,"u":1.616,"v":-3.261},{"lat":65,"lng":-70,"u":0.542,"v":-1.686},{"lat":65,"lng":-65,"u":2.323,"v":-1.176},{"lat":65,"lng":-60,"u":3.471,"v":-2.3},{"lat":65,"lng":-55,"u":1.738,"v":-2.968},{"lat":65,"lng":-50,"u":0.518,"v":-1.708},{"lat":65,"lng":-45,"u":2.201,"v":0.024},{"lat":65,"lng":-40,"u":3.49,"v":0.1},{"lat":65,"lng":-35,"u":1.861,"v":-0.971},{"lat":65,"lng":-30,"u":0.504,"v":-0.859},{"lat":65,"lng":-25,"u":2.076,"v":0.928},{"lat":65,"lng":-20,"u":3.499,"v":2.256},{"lat":65,"lng":-15,"u":1.986,"v":1.678},{"lat":65,"lng":-10,"u":0.5,"v":0.675},{"lat":65,"lng":-5,"u":1.952,"v":1.325},{"lat":65,"lng":0,"u":3.498,"v":3.042},{"lat":65,"lng":5,"u":2.111,"v":3.478},{"lat":65,"lng":10,"u":0.507,"v":2.18},{"lat":65,"lng":15,"u":1.827,"v":1.292},{"lat":65,"lng":20,"u":3.486,"v":2.2},{"lat":65,"lng":25,"u":2.235,"v":3.371},{"lat":65,"lng":30,"u":0.524,"v":2.746},{"lat":65,"lng":35,"u":1.704,"v":0.969},{"lat":65,"lng":40,"u":3.464,"v":0.385},{"lat":65,"lng":45,"u":2.357,"v":1.396},{"lat":65,"lng":50,"u":0.551,"v":1.844},{"lat":65,"lng":55,"u":1.583,"v":0.402},{"lat":65,"lng":60,"u":3.432,"v":-1.334},{"lat":65,"lng":65,"u":2.477,"v":-1.321},{"lat":65,"lng":70,"u":0.588,"v":-0.235},{"lat":65,"lng":75,"u":1.465,"v":-0.401},{"lat":65,"lng":80,"u":3.39,"v":-2.137},{"lat":65,"lng":85,"u":2.593,"v":-3.243},{"lat":65,"lng":90,"u":0.635,"v":-2.42},{"lat":65,"lng":95,"u":1.35,"v":-1.288},{"lat":65,"lng":100,"u":3.338,"v":-1.842},{"lat":65,"lng":105,"u":2.706,"v":-3.334},{"lat":65,"lng":110,"u":0.691,"v":-3.433},{"lat":65,"lng":115,"u":1.24,"v":-1.868},{"lat":65,"lng":120,"u":3.277,"v":-0.856},{"lat":65,"lng":125,"u":2.813,"v":-1.643},{"lat":65,"lng":130,"u":0.757,"v":-2.571},{"lat":65,"lng":135,"u":1.135,"v":-1.679},{"lat":65,"lng":140,"u":3.207,"v":0.217},{"lat":65,"lng":145,"u":2.915,"v":0.783},{"lat":65,"lng":150,"u":0.831,"v":-0.208},{"lat":65,"lng":155,"u":1.036,"v":-0.541},{"lat":65,"lng":160,"u":3.129,"v":0.962},{"lat":65,"lng":165,"u":3.011,"v":2.581},{"lat":65,"lng":170,"u":0.913,"v":2.364},{"lat":65,"lng":175,"u":0.944,"v":1.163},{"lat":65,"lng":180,"u":3.043,"v":1.281},{"lat":70,"lng":-180,"u":-2.741,"v":2.782},{"lat":70,"lng":-175,"u":-0.712,"v":3.649},{"lat":70,"lng":-170,"u":-1.205,"v":2.587},{"lat":70,"lng":-165,"u":-3.255,"v":1.313},{"lat":70,"lng":-160,"u":-2.847,"v":1.759},{"lat":70,"lng":-155,"u":-0.78,"v":3.055},{"lat":70,"lng":-150,"u":-1.102,"v":2.895},{"lat":70,"lng":-145,"u":-3.183,"v":1.146},{"lat":70,"lng":-140,"u":-2.947,"v":0.068},{"lat":70,"lng":-135,"u":-0.857,"v":0.798},{"lat":70,"lng":-130,"u":-1.006,"v":1.591},{"lat":70,"lng":-125,"u":-3.102,"v":0.564},{"lat":70,"lng":-120,"u":-3.04,"v":-1.344},{"lat":70,"lng":-115,"u":-0.941,"v":-1.817},{"lat":70,"lng":-110,"u":-0.916,"v":-0.761},{"lat":70,"lng":-105,"u":-3.014,"v":-0.431},{"lat":70,"lng":-100,"u":-3.126,"v":-1.889},{"lat":70,"lng":-95,"u":-1.033,"v":-3.33},{"lat":70,"lng":-90,"u":-0.833,"v":-2.886},{"lat":70,"lng":-85,"u":-2.918,"v":-1.532},{"lat":70,"lng":-80,"u":-3.205,"v":-1.556},{"lat":70,"lng":-75,"u":-1.132,"v":-2.978},{"lat":70,"lng":-70,"u":-0.759,"v":-3.519},{"lat":70,"lng":-65,"u":-2.817,"v":-2.161},{"lat":70,"lng":-60,"u":-3.275,"v":-0.743},{"lat":70,"lng":-55,"u":-1.236,"v":-1.097},{"lat":70,"lng":-50,"u":-0.693,"v":-2.199},{"lat":70,"lng":-45,"u":-2.709,"v":-1.78},{"lat":70,"lng":-40,"u":-3.336,"v":0.109},{"lat":70,"lng":-35,"u":-1.346,"v":1.163},{"lat":70,"lng":-30,"u":-0.637,"v":0.4},{"lat":70,"lng":-25,"u":-2.597,"v":-0.323},{"lat":70,"lng":-20,"u":-3.388,"v":0.768},{"lat":70,"lng":-15,"u":-1.461,"v":2.574},{"lat":70,"lng":-10,"u":-0.589,"v":2.82},{"lat":70,"lng":-5,"u":-2.481,"v":1.595},{"lat":70,"lng":0,"u":-3.431,"v":1.194},{"lat":70,"lng":5,"u":-1.579,"v":2.526},{"lat":70,"lng":10,"u":-0.552,"v":3.683},{"lat":70,"lng":15,"u":-2.361,"v":2.916},{"lat":70,"lng":20,"u":-3.463,"v":1.365},{"lat":70,"lng":25,"u":-1.7,"v":1.28},{"lat":70,"lng":30,"u":-0.524,"v":2.512},{"lat":70,"lng":35,"u":-2.239,"v":2.754},{"lat":70,"lng":40,"u":-3.486,"v":1.156},{"lat":70,"lng":45,"u":-1.823,"v":-0.333},{"lat":70,"lng":50,"u":-0.507,"v":0.008},{"lat":70,"lng":55,"u":-2.115,"v":1.001},{"lat":70,"lng":60,"u":-3.498,"v":0.43},{"lat":70,"lng":65,"u":-1.948,"v":-1.478},{"lat":70,"lng":70,"u":-0.5,"v":-2.387},{"lat":70,"lng":75,"u":-1.99,"v":-1.482},{"lat":70,"lng":80,"u":-3.499,"v":-0.723},{"lat":70,"lng":85,"u":-2.072,"v":-1.768},{"lat":70,"lng":90,"u":-0.504,"v":-3.367},{"lat":70,"lng":95,"u":-1.865,"v":-3.305},{"lat":70,"lng":100,"u":-3.491,"v":-1.852},{"lat":70,"lng":105,"u":-2.197,"v":-1.335},{"lat":70,"lng":110,"u":-0.517,"v":-2.504},{"lat":70,"lng":115,"u":-1.742,"v":-3.36},{"lat":70,"lng":120,"u":-3.472,"v":-2.284},{"lat":70,"lng":125,"u":-2.319,"v":-0.574},{"lat":70,"lng":130,"u":-0.541,"v":-0.429},{"lat":70,"lng":135,"u":-1.62,"v":-1.529},{"lat":70,"lng":140,"u":-3.443,"v":-1.551},{"lat":70,"lng":145,"u":-2.44,"v":0.185},{"lat":70,"lng":150,"u":-0.575,"v":1.631},{"lat":70,"lng":155,"u":-1.501,"v":1.195},{"lat":70,"lng":160,"u":-3.404,"v":0.202},{"lat":70,"lng":165,"u":-2.558,"v":0.808},{"lat":70,"lng":170,"u":-0.619,"v":2.614},{"lat":70,"lng":175,"u":-1.385,"v":3.27},{"lat":70,"lng":180,"u":-3.355,"v":2.135}]